Workbook

Sheet 日淘
A1: IP | B1: 系列名称 | C1: 名称 | D1: 买时状态 | E1: 购入价格 | F1: 运费 | G1: 状态 | H1: 缴税 | I1: 总价 | J1: 成本价格 | K1: 卖出价格 | L1: 利润 | M1: 利润率 | N1: 备注 | O1: 卖否 | P1: 转运单号
A2: 龙珠 | B2: MSP | C2: 超赛悟空 | D2: 拆摆 | E2: 153 | F2: 41 | G2: 卖出 | I2: =(E2+F2+H2) -> 194 | J2: 194 | K2: 165 | L2: =(K2-J2) -> -29 | M2: =ROUND(L2/J2,4) -> -0.1495
A3: 龙珠 | B3: Grandista | C3: 超赛贝吉塔 | D3: 拆摆 | E3: 433 | F3: 84 | G3: 留存 | I3: =(E3+F3+H3) -> 517 | Q3: 总花销 | R3: =SUM(I:I) -> 148144
A4: 龙珠 | B4: 武道会3 | C4: 人造人18号 | D4: 拆摆 | E4: 230 | F4: 23 | G4: 留存 | I4: =(E4+F4+H4) -> 253 | Q4: 总卖出 | R4: =SUM(K:K) -> 95089
A5: 龙珠 | B5: Grandista | C5: 超赛悟空 | D5: 全新 | E5: 435 | F5: 73 | G5: 留存 | H5: 17 | I5: =(E5+F5+H5) -> 525 | Q5: 总卖出成本 | R5: =SUM(J:J) -> 84382
A6: 龙珠 | B6: MSP | C6: 超赛悟空 | D6: 全新 | E6: 194 | F6: 50 | G6: 留存 | H6: 17 | I6: =(E6+F6+H6) -> 261 | Q6: 利润 | R6: =SUM(L:L) -> 10707
A7: 龙珠 | B7: 武道会3 | C7: 龟仙人 | D7: 拆摆 | E7: 397 | F7: 28 | G7: 留存 | H7: 17 | I7: =(E7+F7+H7) -> 442 | Q7: 利润率 | R7: =ROUND(R6/R5,4) -> 0.1269
A8: 龙珠 | B8: 一番赏 | C8: 宇航服悟饭克林 | D8: 全新 | E8: 242 | F8: 62 | G8: 卖出 | I8: =(E8+F8+H8) -> 304 | J8: =I8 -> 304 | K8: 365 | L8: =(K8-J8) -> 61 | M8: =ROUND(L8/J8,4) -> 0.2007 | N8: set | Q8: 实际支出 | R8: =R3-R4 -> 53055
A9: 龙珠 | B9: SMSP | C9: 棍空C赏 | D9: 拆摆 | E9: 855 | F9: 27 | G9: 卖出 | H9: 19 | I9: =(E9+F9+H9) -> 901 | J9: =I9 -> 901 | K9: 1100 | L9: =(K9-J9) -> 199 | M9: =ROUND(L9/J9,4) -> 0.2209
A10: 龙珠 | B10: MSP | C10: 超赛特兰克斯 | D10: 拆摆 | E10: 271 | F10: 27 | G10: 留存 | H10: 19 | I10: =(E10+F10+H10) -> 317
A11: 鬼灭之刃 | B11: 一番赏 | C11: 甘露寺蜜璃A赏 | D11: 全新 | E11: 133 | F11: 15 | G11: 留存 | H11: 19 | I11: =(E11+F11+H11) -> 167
A12: 鬼灭之刃 | B12: 一番赏 | C12: 时透无一郎B赏 | D12: 全新 | E12: 178 | F12: 12 | G12: 留存 | H12: 19 | I12: =(E12+F12+H12) -> 209
A13: 龙珠 | B13: 一番赏 | C13: 激突 （小布欧+悟饭+赛亚超人悟饭+达普拉） | D13: 全新 | E13: 1125 | F13: 99 | G13: 留存 | H13: 70 | I13: =(E13+F13+H13) -> 1294 | N13: set
A14: 龙珠 | B14: SMSP | C14: 棍空C赏 | D14: 全新 | E14: 1075 | F14: 50 | G14: 卖出 | H14: 19 | I14: =(E14+F14+H14) -> 1144 | J14: =I14 -> 1144 | K14: 1160 | L14: =(K14-J14) -> 16 | M14: =ROUND(L14/J14,4) -> 0.014
A15: 龙珠 | B15: 一番赏 | C15: 多多利亚 | D15: 拆摆 | E15: 401 | F15: 82 | G15: 卖出 | H15: 19 | I15: =(E15+F15+H15) -> 502 | J15: =I15 -> 502 | K15: 679 | L15: =(K15-J15) -> 177 | M15: =ROUND(L15/J15,4) -> 0.3526 | N15: 无桩
A16: 沙漠大冒险 | B16: 一番赏 | C16: 贝尔杰布A赏 | D16: 全新 | E16: 262 | F16: 17 | G16: 卖出 | H16: 19 | I16: =(E16+F16+H16) -> 298 | J16: 298 | K16: 298 | L16: =(K16-J16) -> 0 | M16: =ROUND(L16/J16,4) -> 0
A17: 沙漠大冒险 | B17: 一番赏 | C17: 贝尔杰布A赏 | D17: 全新 | E17: 265 | F17: 18 | G17: 留存 | H17: 19 | I17: =(E17+F17+H17) -> 302
A18: 龙珠 | B18: LC | C18: 特兰克斯 | D18: 全新 | E18: 248 | F18: 18 | G18: 留存 | H18: 46 | I18: =(E18+F18+H18) -> 312
A19: 龙珠 | B19: 一番赏 | C19: 弗利萨第二形态 | D19: 全新 | E19: 287 | F19: 41 | G19: 卖出 | H19: 46 | I19: =(E19+F19+H19) -> 374 | J19: =I19 -> 374 | K19: 440 | L19: =(K19-J19) -> 66 | M19: =ROUND(L19/J19,4) -> 0.1765
A20: 龙珠 | B20: PLEX | C20: 弗利萨第三形态 | D20: 全新 | E20: 1736 | F20: 62 | G20: 卖出 | H20: 47 | I20: =(E20+F20+H20) -> 1845 | J20: 1845 | K20: 2300 | L20: =(K20-J20) -> 455 | M20: =ROUND(L20/J20,4) -> 0.2466 | N20: 特典版
A21: 龙珠 | B21: 一番赏 | C21: LB悟空最终赏 | D21: 全新 | E21: 401 | F21: 54 | G21: 留存 | H21: 47 | I21: =(E21+F21+H21) -> 502
A22: 龙珠 | B22: 一番赏 | C22: LB悟空最终赏 | D22: 内袋未拆 | E22: 383 | F22: 69 | G22: 卖出 | H22: 25 | I22: =(E22+F22+H22) -> 477 | J22: =I22 -> 477 | K22: 540 | L22: =(K22-J22) -> 63 | M22: =ROUND(L22/J22,4) -> 0.1321
A23: 龙珠 | B23: PLEX | C23: 弗利萨第三形态 | D23: 拆摆 | E23: 1159 | F23: 77 | G23: 卖出 | H23: 25 | I23: =(E23+F23+H23) -> 1261 | J23: =I23 -> 1261 | K23: 1560 | L23: =(K23-J23) -> 299 | M23: =ROUND(L23/J23,4) -> 0.2371 | N23: 普通版
A24: 龙珠 | B24: 一番赏 | C24: 宇航服布玛 | D24: 全新 | E24: 307 | F24: 34 | G24: 卖出 | H24: 25 | I24: =(E24+F24+H24) -> 366 | J24: =I24 -> 366 | K24: 392 | L24: =(K24-J24) -> 26 | M24: =ROUND(L24/J24,4) -> 0.071
A25: 龙珠 | B25: SMSP | C25: 棍空C赏 | D25: 全新 | E25: 972 | F25: 54 | G25: 留存 | H25: 27 | I25: =(E25+F25+H25) -> 1053
A26: 龙珠 | B26: 一番赏 | C26: 宇航服悟饭克林 | D26: 全新 | E26: 245 | F26: 29 | G26: 卖出 | H26: 27 | I26: =(E26+F26+H26) -> 301 | J26: 301 | K26: 399 | L26: =(K26-J26) -> 98 | M26: =ROUND(L26/J26,4) -> 0.3256 | N26: set
A27: 龙珠 | B27: 一番赏 | C27: 宇航服悟饭克林 | D27: 全新 | E27: 253 | F27: 30 | G27: 卖出 | H27: 27 | I27: =(E27+F27+H27) -> 310 | J27: 310 | K27: 379 | L27: =(K27-J27) -> 69 | M27: =ROUND(L27/J27,4) -> 0.2226 | N27: set
A28: 龙珠 | B28: 一番赏 | C28: 宇航服布玛 | D28: 全新 | E28: 234 | F28: 37 | G28: 卖出 | H28: 27 | I28: =(E28+F28+H28) -> 298 | J28: =I28 -> 298 | K28: 384 | L28: =(K28-J28) -> 86 | M28: =ROUND(L28/J28,4) -> 0.2886
A29: 龙珠 | B29: PLEX | C29: 大长老 | D29: 全新 | E29: 3846 | F29: 225 | G29: 卖出 | H29: 89 | I29: =(E29+F29+H29) -> 4160 | J29: 4160 | K29: 3400 | L29: =(K29-J29) -> -760 | M29: =ROUND(L29/J29,4) -> -0.1827 | N29: 特典版
A30: 龙珠 | B30: 一番赏 | C30: 邱夷 | D30: 全新 | E30: 327 | F30: 18 | G30: 卖出 | I30: =(E30+F30+H30) -> 345 | J30: 345 | K30: 429 | L30: =(K30-J30) -> 84 | M30: =ROUND(L30/J30,4) -> 0.2435
A31: 龙珠 | B31: 一番赏 | C31: 邱夷 | D31: 全新 | E31: 323 | F31: 18 | G31: 卖出 | I31: =(E31+F31+H31) -> 341 | J31: 341 | K31: 450 | L31: =(K31-J31) -> 109 | M31: =ROUND(L31/J31,4) -> 0.3196
A32: 龙珠 | B32: 一番赏 | C32: 多多利亚 | D32: 全新 | E32: 551 | F32: 58 | G32: 留存 | I32: =(E32+F32+H32) -> 609
A33: 龙珠 | B33: 一番赏 | C33: 宇航服悟饭克林 | D33: 全新 | E33: 278 | F33: 29 | G33: 卖出 | H33: 38 | I33: =(E33+F33+H33) -> 345 | J33: 345 | K33: 386 | L33: =(K33-J33) -> 41 | M33: =ROUND(L33/J33,4) -> 0.1188 | N33: set
A34: 龙珠 | B34: 一番赏 | C34: lb贝吉塔 | D34: 全新 | E34: 747 | F34: 38 | G34: 卖出 | H34: 38 | I34: =(E34+F34+H34) -> 823 | J34: 823 | K34: 950 | L34: =(K34-J34) -> 127 | M34: =ROUND(L34/J34,4) -> 0.1543 | N34: 盒有轻损
A35: 龙珠 | B35: 一番赏 | C35: 宇航服布玛 | D35: 全新 | E35: 278 | F35: 34 | G35: 卖出 | H35: 38 | I35: =(E35+F35+H35) -> 350 | J35: =I35 -> 350 | K35: 386 | L35: =(K35-J35) -> 36 | M35: =ROUND(L35/J35,4) -> 0.1029
A36: 龙珠 | B36: PLEX | C36: 弗利萨第三形态 | D36: 全新 | E36: 1765 | F36: 74 | G36: 卖出 | H36: 39 | I36: =(E36+F36+H36) -> 1878 | J36: 1878 | K36: 2100 | L36: =(K36-J36) -> 222 | M36: =ROUND(L36/J36,4) -> 0.1182 | N36: 特典版
A37: 龙珠 | B37: 一番赏 | C37: 宇航服悟饭克林 | D37: 全新 | E37: 249 | F37: 32 | G37: 卖出 | H37: 36 | I37: =(E37+F37+H37) -> 317 | J37: 317 | K37: 399 | L37: =(K37-J37) -> 82 | M37: =ROUND(L37/J37,4) -> 0.2587 | N37: set
A38: 龙珠 | B38: 一番赏 | C38: 宇航服悟饭克林 | D38: 全新 | E38: 246 | F38: 33 | G38: 卖出 | H38: 36 | I38: =(E38+F38+H38) -> 315 | J38: 315 | K38: 395 | L38: =(K38-J38) -> 80 | M38: =ROUND(L38/J38,4) -> 0.254 | N38: set
A39: 龙珠 | B39: PLEX | C39: 弗利萨第三形态 | D39: 全新 | E39: 1696 | F39: 81 | G39: 卖出 | H39: 37 | I39: =(E39+F39+H39) -> 1814 | J39: 1814 | K39: 2129 | L39: =(K39-J39) -> 315 | M39: =ROUND(L39/J39,4) -> 0.1736 | N39: 特典版
A40: 偶像大师灰姑娘女孩 | B40: Alter | C40: 宫本芙蕾德莉卡 | D40: 全新 | E40: 724 | F40: 19 | G40: 留存 | H40: 37 | I40: =(E40+F40+H40) -> 780
A41: 龙珠 | B41: PLEX | C41: 大长老 | D41: 全新 | E41: 3898 | F41: 136 | G41: 卖出 | H41: 90 | I41: =(E41+F41+H41) -> 4124 | J41: 4124 | K41: 3300 | L41: =(K41-J41) -> -824 | M41: =ROUND(L41/J41,4) -> -0.1998 | N41: 特典版 | P41: 100117-2152
A42: 龙珠 | B42: 一番赏 | C42: LB贝吉塔 | D42: 拆摆 | E42: 637 | F42: 23 | G42: 卖出 | H42: 40 | I42: =(E42+F42+H42) -> 700 | J42: 700 | K42: 750 | L42: =(K42-J42) -> 50 | M42: =ROUND(L42/J42,4) -> 0.0714
A43: 龙珠 | B43: 一番赏 | C43: 宇航服悟饭 | D43: 拆摆 | E43: 110 | F43: 25 | G43: 卖出 | I43: =(E43+F43+H43) -> 135 | J43: =I43 -> 135 | K43: 190 | L43: =(K43-J43) -> 55 | M43: =ROUND(L43/J43,4) -> 0.4074 | N43: 悟饭拆摆，克林全新，set（悟饭和拼多多克林一起卖掉）
A44: 龙珠 | B44: PLEX | C44: 吐蛋比克 | D44: 全新 | E44: 1103 | F44: 63 | G44: 卖出 | H44: 41 | I44: =(E44+F44+H44) -> 1207 | J44: =I44 -> 1207 | K44: 1700 | L44: =(K44-J44) -> 493 | M44: =ROUND(L44/J44,4) -> 0.4085 | N44: 特典版
A45: 龙珠 | B45: 一番赏 | C45: 宇航服布玛 | D45: 全新 | E45: 276 | F45: 17 | G45: 卖出 | H45: 41 | I45: =(E45+F45+H45) -> 334 | J45: =I45 -> 334 | K45: 409 | L45: =(K45-J45) -> 75 | M45: =ROUND(L45/J45,4) -> 0.2246
A46: 龙珠 | B46: 武道会2 | C46: 牛魔王 | D46: 全新 | E46: 306 | F46: 18 | G46: 留存 | H46: 28 | I46: =(E46+F46+H46) -> 352 | P46: 091202-7946
A47: 龙珠 | B47: 武道会2 | C47: 琪琪 | D47: 拆摆 | E47: 328 | F47: 21 | G47: 留存 | H47: 29 | I47: =(E47+F47+H47) -> 378 | N47: 无盒 | O47: 待定 | P47: 091202-7946
A48: 龙珠 | B48: 一番赏 | C48: 宇航服悟饭克林 | D48: 全新 | E48: 257 | F48: 23 | G48: 卖出 | H48: 29 | I48: =(E48+F48+H48) -> 309 | J48: 309 | K48: 399 | L48: =(K48-J48) -> 90 | M48: =ROUND(L48/J48,4) -> 0.2913 | N48: set | P48: 091202-7946
A49: 龙珠 | B49: PLEX | C49: 弗利萨第三形态 | D49: 拆摆 | E49: 1641 | F49: 46 | G49: 卖出 | H49: 29 | I49: =(E49+F49+H49) -> 1716 | J49: 1716 | K49: 1620 | L49: =(K49-J49) -> -96 | M49: =ROUND(L49/J49,4) -> -0.0559 | N49: 特典版 | P49: 091202-7946
A50: 龙珠 | B50: 一番赏 | C50: 武道会 档案馆 | D50: 全新 | E50: 108 | F50: 5 | G50: 留存 | H50: 28 | I50: =(E50+F50+H50) -> 141 | N50: 缺沈先生 | P50: 091202-7946
A51: 龙珠 | B51: PLEX | C51: 内鲁 | D51: 全新 | E51: 2033 | F51: 50 | G51: 卖出 | H51: 37 | I51: =(E51+F51+H51) -> 2120 | J51: 2120 | K51: 2088 | L51: =(K51-J51) -> -32 | M51: =ROUND(L51/J51,4) -> -0.0151 | N51: 特典版
A52: 龙珠 | B52: 一番赏 | C52: 小布欧+赛亚超人 | D52: 全新 | E52: 456 | F52: 53 | G52: 卖出 | H52: 37 | I52: =(E52+F52+H52) -> 546 | J52: 546 | K52: 655 | L52: =(K52-J52) -> 109 | M52: =ROUND(L52/J52,4) -> 0.1996 | N52: set(225+430)
A53: 龙珠 | B53: 一番赏 | C53: 宇航服布玛 | D53: 全新 | E53: 276 | F53: 20 | G53: 卖出 | H53: 37 | I53: =(E53+F53+H53) -> 333 | J53: =I53 -> 333 | K53: 400 | L53: =(K53-J53) -> 67 | M53: =ROUND(L53/J53,4) -> 0.2012
A54: 龙珠 | B54: PLEX | C54: 大鼓 | D54: 拆摆 | E54: 1333 | F54: 28 | G54: 卖出 | H54: 56 | I54: =(E54+F54+H54) -> 1417 | J54: 1417 | K54: 1597 | L54: =(K54-J54) -> 180 | M54: =ROUND(L54/J54,4) -> 0.127 | N54: 普通版
A55: 龙珠 | B55: 一番赏 | C55: 贝吉塔大猿 | D55: 全新 | E55: 1100 | F55: 37 | G55: 留存 | H55: 46 | I55: =(E55+F55+H55) -> 1183 | N55: 外袋有些许破损
A56: 迪士尼 | B56: 玩偶 | C56: 东京春日贝尔 | D56: 全新 | E56: 147 | F56: 1 | G56: 留存 | H56: 6 | I56: =(E56+F56+H56) -> 154
A57: 龙珠 | B57: PLEX | C57: 比克大魔王 | D57: 全新 | E57: 877 | F57: 75 | G57: 卖出 | H57: 69 | I57: =(E57+F57+H57) -> 1021 | J57: 1021 | K57: 1610 | L57: =(K57-J57) -> 589 | M57: =ROUND(L57/J57,4) -> 0.5769 | N57: 普通版 | P57: 090103-8234
A58: 龙珠 | B58: BWFC | C58: 弗利萨 | D58: 全新 | E58: 209 | F58: 10 | G58: 留存 | H58: 16 | I58: =(E58+F58+H58) -> 235 | P58: 090103-8234
A59: 龙珠 | B59: 一番赏 | C59: 弗利萨军团 档案馆 | D59: 全新 | E59: 151 | F59: 6 | G59: 留存 | H59: 11 | I59: =(E59+F59+H59) -> 168 | N59: 一套全 | P59: 090103-8234
A60: 龙珠 | B60: 一番赏 | C60: 弗利萨婴儿车last | D60: 拆摆 | E60: 751 | F60: 18 | G60: 留存 | H60: 56 | I60: =(E60+F60+H60) -> 825 | N60: 重涂扉页色 | P60: 090103-8234
A61: 龙珠 | B61: PLEX | C61: 弗利萨第三形态 | D61: 全新 | E61: 1315 | F61: 47 | G61: 卖出 | H61: 73 | I61: =(E61+F61+H61) -> 1435 | J61: 1435 | K61: 1569 | L61: =(K61-J61) -> 134 | M61: =ROUND(L61/J61,4) -> 0.0934 | N61: 普通版 | P61: 090110-7585
A62: 龙珠 | B62: 一番赏 | C62: 宇航服布玛 | D62: 全新 | E62: 236 | F62: 20 | G62: 留存 | H62: 13 | I62: =(E62+F62+H62) -> 269 | P62: 090110-7585
A63: 龙珠 | B63: 一番赏 | C63: LB贝吉塔 | D63: 全新 | E63: 740 | F63: 19 | G63: 留存 | H63: 41 | I63: =(E63+F63+H63) -> 800 | N63: 盒有轻损 | P63: 090110-7585
A64: 龙珠 | B64: Grandista | C64: 超赛悟空 | D64: 拆摆 | E64: 222 | F64: 19 | G64: 卖出 | H64: 13 | I64: =(E64+F64+H64) -> 254 | J64: 254 | K64: 369 | L64: =(K64-J64) -> 115 | M64: =ROUND(L64/J64,4) -> 0.4528 | N64: 无盒 | P64: 090110-7585
A65: 龙珠 | B65: 一番赏 | C65: 宇航服库林 | D65: 内袋未拆 | E65: 120 | F65: 40 | G65: 卖出 | I65: =(E65+F65+H65) -> 160 | J65: 160 | K65: 168 | L65: =(K65-J65) -> 8 | M65: =ROUND(L65/J65,4) -> 0.05
A66: 龙珠 | B66: 一番赏 | C66: 宇航服悟饭 | D66: 全新 | E66: 233 | F66: 45 | G66: 留存 | I66: =(E66+F66+H66) -> 278 | N66: 2个 | O66: 卖
A67: 龙珠 | B67: 一番赏 | C67: 未来的决斗（last+悟饭+特兰克斯+沙鲁+贝吉塔） | D67: 全新 | E67: 1426 | F67: 163 | G67: 卖出 | H67: 105 | I67: =(E67+F67+H67) -> 1694 | J67: 1694 | K67: 2020 | L67: =(K67-J67) -> 326 | M67: =ROUND(L67/J67,4) -> 0.1924 | P67: docobuy
A68: 龙珠 | B68: 一番赏 | C68: 邱夷 | D68: 全新 | E68: 321 | F68: 28 | G68: 留存 | H68: 14 | I68: =(E68+F68+H68) -> 363 | P68: docobuy
A69: 龙珠 | B69: 一番赏 | C69: 大猿套小布欧 | D69: 全新 | E69: 750 | F69: 28 | G69: 留存 | H69: 33 | I69: =(E69+F69+H69) -> 811 | P69: docobuy
A70: 龙珠 | B70: 一番赏 | C70: 弗利萨第二形态 | D70: 全新 | E70: 306 | F70: 54 | G70: 留存 | H70: 13 | I70: =(E70+F70+H70) -> 373 | P70: docobuy
A71: 龙珠 | B71: PLEX | C71: 弗利萨第三形态 | D71: 全新 | E71: 1692 | F71: 72 | G71: 留存 | H71: 74 | I71: =(E71+F71+H71) -> 1838 | N71: 特典版 | P71: docobuy
A72: 龙珠 | B72: 一番赏 | C72: 弗利萨第三形态 | D72: 拆摆 | E72: 267 | F72: 67 | G72: 留存 | I72: =(E72+F72+H72) -> 334 | P72: docobuy
A73: 龙珠 | B73: 一番赏 | C73: 桃红假面超三A赏 | D73: 全新 | E73: 184 | F73: 68 | G73: 卖出 | I73: =(E73+F73+H73) -> 252 | J73: 252 | K73: 321 | L73: =(K73-J73) -> 69 | M73: =ROUND(L73/J73,4) -> 0.2738 | P73: docobuy
A74: 龙珠 | B74: 一番赏 | C74: 龟仙流 档案馆 | D74: 全新 | E74: 121 | F74: 4 | G74: 留存 | H74: 3 | I74: =(E74+F74+H74) -> 128 | N74: 一套全 | P74: 090107-5584
A75: 龙珠 | B75: PLEX | C75: 大鼓 | D75: 全新 | E75: 2212 | F75: 48 | G75: 卖出 | H75: 56 | I75: =(E75+F75+H75) -> 2316 | J75: 2316 | K75: 2800 | L75: =(K75-J75) -> 484 | M75: =ROUND(L75/J75,4) -> 0.209 | N75: 普通色特典版 | P75: 090107-5584
A76: 龙珠 | B76: PLEX | C76: 辛巴鲁 | D76: 全新 | E76: 1545 | F76: 69 | G76: 卖出 | H76: 39 | I76: =(E76+F76+H76) -> 1653 | J76: 1653 | K76: 2200 | L76: =(K76-J76) -> 547 | M76: =ROUND(L76/J76,4) -> 0.3309 | N76: 普通色特典版 | P76: 090107-5584
A77: 龙珠 | B77: 一番赏 | C77: 未来的决斗（last+沙鲁+贝吉塔） | D77: 全新 | E77: 1125 | F77: 129 | G77: 卖出 | H77: 137 | I77: =(E77+F77+H77) -> 1391 | J77: 1391 | K77: 1299 | L77: =(K77-J77) -> -92 | M77: =ROUND(L77/J77,4) -> -0.0661 | P77: 090103-7164
A78: 龙珠 | B78: 食玩 | C78: 4人（贝吉塔+悟空+库林+雅木茶） | D78: 全新 | E78: 84 | F78: 2 | G78: 留存 | H78: 10 | I78: =(E78+F78+H78) -> 96 | P78: 090103-7164
A79: 龙珠 | B79: 一番赏 | C79: 宇航服悟饭 | D79: 全新 | E79: 114 | F79: 10 | G79: 卖出 | H79: 14 | I79: =(E79+F79+H79) -> 138 | J79: 138 | K79: 195 | L79: =(K79-J79) -> 57 | M79: =ROUND(L79/J79,4) -> 0.413 | P79: 090103-7164
A80: 龙珠 | B80: 一番赏 | C80: 宇航服克林 | D80: 拆摆 | E80: 123 | F80: 17 | G80: 卖出 | H80: 15 | I80: =(E80+F80+H80) -> 155 | J80: 155 | K80: 166 | L80: =(K80-J80) -> 11 | M80: =ROUND(L80/J80,4) -> 0.071 | P80: 090103-7164
A81: 龙珠 | B81: PLEX | C81: 多多利亚 | D81: 全新 | E81: 1290 | F81: 87 | G81: 卖出 | H81: 61 | I81: =(E81+F81+H81) -> 1438 | J81: 1438 | K81: 1650 | L81: =(K81-J81) -> 212 | M81: =ROUND(L81/J81,4) -> 0.1474 | N81: 老妈的号 | P81: 090107-9476
A82: 龙珠 | B82: 一番赏 | C82: 父子机车B赏 | D82: 全新 | E82: 1192 | F82: 26 | G82: 卖出 | H82: 56 | I82: =(E82+F82+H82) -> 1274 | J82: 1274 | K82: 1183 | L82: =(K82-J82) -> -91 | M82: =ROUND(L82/J82,4) -> -0.0714 | N82: 老妈的号 | P82: 090107-9476
A83: 沙漠大冒险 | B83: 一番赏 | C83: 贝尔杰布last赏 | D83: 全新 | E83: 331 | F83: 18 | G83: 留存 | H83: 16 | I83: =(E83+F83+H83) -> 365 | N83: 老妈的号 | P83: 090107-9476
A84: 间谍过家家 | B84: GSC | C84: 约尔 与 阿尼亚 | D84: 全新 | E84: 647 | F84: 37 | G84: 留存 | H84: 31 | I84: =(E84+F84+H84) -> 715 | N84: 老妈的号 | P84: 090107-9476
A85: 龙珠 | B85: 一番赏 | C85: 武道会主持人 | D85: 全新 | E85: 173 | F85: 22 | G85: 留存 | H85: 18 | I85: =(E85+F85+H85) -> 213 | P85: 090107-7247
A86: 龙珠 | B86: 一番赏 | C86: 未来的决斗 撒旦 | D86: 全新 | E86: 182 | F86: 37 | G86: 卖出 | H86: 19 | I86: =(E86+F86+H86) -> 238 | J86: 238 | K86: 239 | L86: =(K86-J86) -> 1 | M86: =ROUND(L86/J86,4) -> 0.0042 | P86: 090107-7247
A87: 龙珠 | B87: 一番赏 | C87: 未来的决斗全套1 | D87: 全新 | E87: 1023 | F87: 105 | G87: 留存 | H87: 75 | I87: =(E87+F87+H87) -> 1203 | J87: 371 | K87: 465 | L87: =(K87-J87) -> 94 | M87: =ROUND(L87/J87,4) -> 0.2534 | N87: last(832)+贝吉塔(185)+特兰克斯（186），特兰克斯贝吉塔卖出，相当于last（738） | P87: 090107-7247
A88: 龙珠 | B88: 一番赏 | C88: 武道会主持人 | D88: 全新 | E88: 192 | F88: 26 | G88: 卖出 | H88: 19 | I88: =(E88+F88+H88) -> 237 | J88: 237 | K88: 180 | L88: =(K88-J88) -> -57 | M88: =ROUND(L88/J88,4) -> -0.2405 | P88: 090108-4445
A89: 龙珠 | B89: 一番赏 | C89: 武道会琪琪 | D89: 全新 | E89: 250 | F89: 25 | G89: 留存 | H89: 25 | I89: =(E89+F89+H89) -> 300 | P89: 090108-4445
A90: 龙珠 | B90: 一番赏 | C90: 武道会A悟空+last悟空+比克 | D90: 全新 | E90: 596 | F90: 122 | G90: 留存 | H90: 60 | I90: =(E90+F90+H90) -> 778 | N90: set | P90: 090108-4445
A91: 龙珠 | B91: 一番赏 | C91: 大猿套小布欧 | D91: 拆摆 | E91: 592 | F91: 15 | G91: 卖出 | H91: 59 | I91: =(E91+F91+H91) -> 666 | J91: 666 | K91: 618 | L91: =(K91-J91) -> -48 | M91: =ROUND(L91/J91,4) -> -0.0721 | P91: 090108-4445
A92: 龙珠 | B92: 一番赏 | C92: 萨博 | D92: 全新 | E92: 497 | F92: 75 | G92: 留存 | H92: 60 | I92: =(E92+F92+H92) -> 632 | N92: 亚马逊
A93: 龙珠 | B93: PLEX | C93: 内鲁 | D93: 拆摆 | E93: 1877 | F93: 68 | G93: 卖出 | H93: 83 | I93: =(E93+F93+H93) -> 2028 | J93: 2028 | K93: 1988 | L93: =(K93-J93) -> -40 | M93: =ROUND(L93/J93,4) -> -0.0197 | N93: 特典版
A94: 龙珠 | B94: 一番赏 | C94: 武道会 档案馆 沈先生 | D94: 全新 | E94: 20 | F94: 1 | G94: 留存 | H94: 1 | I94: =(E94+F94+H94) -> 22
A95: 龙珠 | B95: 一番赏 | C95: 宇航服悟饭克林 | D95: 全新 | E95: 252 | F95: 33 | G95: 卖出 | H95: 12 | I95: =(E95+F95+H95) -> 297 | J95: 297 | K95: 388 | L95: =(K95-J95) -> 91 | M95: =ROUND(L95/J95,4) -> 0.3064 | N95: set
A96: 龙珠 | B96: 一番赏 | C96: 超赛悟空 | D96: 全新 | E96: 252 | G96: 留存 | H96: 11 | I96: =(E96+F96+H96) -> 263
A97: 龙珠 | B97: PLEX | C97: 吐蛋比克 | D97: 全新 | E97: 1082 | F97: 87 | G97: 卖出 | H97: 44 | I97: =(E97+F97+H97) -> 1213 | J97: 1213 | K97: 1779 | L97: =(K97-J97) -> 566 | M97: =ROUND(L97/J97,4) -> 0.4666 | N97: 特典版 | P97: 090603-6725
A98: 龙珠 | B98: 武道会3 | C98: 魔人布欧 | D98: 全新 | E98: 343 | F98: 18 | G98: 留存 | H98: 14 | I98: =(E98+F98+H98) -> 375 | P98: 090603-6725
A99: llustration Revelation | C99: 月季鸣珂 | D99: 拆摆 | E99: 680 | F99: 44 | G99: 卖出 | H99: 27 | I99: =(E99+F99+H99) -> 751 | J99: 751 | K99: 860 | L99: =(K99-J99) -> 109 | M99: =ROUND(L99/J99,4) -> 0.1451 | P99: 090603-6725
A100: 龙珠 | B100: 一番赏 | C100: 未来的决斗last | D100: 全新 | E100: 717 | F100: 61 | G100: 卖出 | H100: 42 | I100: =(E100+F100+H100) -> 820 | J100: 820 | K100: 733 | L100: =(K100-J100) -> -87 | M100: =ROUND(L100/J100,4) -> -0.1061 | N100: 老妈的号 | P100: 090108-6674
...

Sheet 闲鱼
A1: IP | B1: 系列名称 | C1: 名称 | D1: 买时状态 | E1: 购入价格 | F1: 运费 | G1: 状态 | H1: 总价 | I1: 成本价格 | J1: 卖出价格 | K1: 利润 | L1: 利润率 | M1: 备注
A2: 数码宝贝 | B2: FRS | C2: 机械邪龙 | D2: 全新 | E2: 330 | G2: 留存 | H2: =(E2+F2) -> 330 | O2: 总花销 | P2: =SUM(H:H) -> 52787
A3: 龙珠 | B3: HG | C3: 基纽特战队 | D3: 拆摆 | E3: 580 | G3: 留存 | H3: =(E3+F3) -> 580 | O3: 总卖出 | P3: =SUM(J:J) -> 5066
A4: 龙珠 | B4: 一番赏 | C4: 基纽 | D4: 全新 | E4: 350 | F4: 45 | G4: 留存 | H4: =(E4+F4) -> 395 | M4: 入坑第一个 | O4: 总卖出成本 | P4: =SUM(I:I) -> 4786
A5: 龙珠 | B5: 一番赏 | C5: 那巴B赏 | D5: 全新 | E5: 168 | G5: 留存 | H5: =(E5+F5) -> 168 | O5: 利润 | P5: =SUM(K:K) -> 280
A6: 鬼灭之刃 | B6: 一番赏 | C6: 炼狱杏寿郎 | D6: 全新 | E6: 214 | G6: 留存 | H6: =(E6+F6) -> 214 | O6: 利润率 | P6: =ROUND(P5/P4,4) -> 0.0585
A7: 鬼灭之刃 | B7: 一番赏 | C7: 富冈义勇 | D7: 全新 | E7: 200 | G7: 留存 | H7: =(E7+F7) -> 200 | O7: 实际支出 | P7: =P2-P3 -> 47721
A8: 鬼灭之刃 | B8: 一番赏 | C8: 蝴蝶忍 | D8: 全新 | E8: 229 | G8: 留存 | H8: =(E8+F8) -> 229
A9: 龙珠 | B9: 一番赏 | C9: 蔬菜人 | D9: 拆摆 | E9: 58 | G9: 留存 | H9: =(E9+F9) -> 58
A10: 龙珠 | B10: 武道会 | C10: 兰琪 | D10: 全新 | E10: 185 | G10: 留存 | H10: =(E10+F10) -> 185
A11: 龙珠 | B11: 一番赏 | C11: 波伦伽 | D11: 拆摆 | E11: 1266 | G11: 留存 | H11: =(E11+F11) -> 1266
A12: 龙珠 | B12: 一番赏 | C12: 抬头龙 | D12: 全新 | E12: 1079 | G12: 留存 | H12: =(E12+F12) -> 1079
A13: 龙珠 | B13: MSP | C13: 悟天克斯 | D13: 全新 | E13: 225 | G13: 留存 | H13: =(E13+F13) -> 225
A14: 龙珠 | B14: BWFC | C14: 虎皮悟空 | D14: 全新 | E14: 226 | F14: 11 | G14: 留存 | H14: =(E14+F14) -> 237
A15: 龙珠 | B15: BWFC | C15: 打伞悟空 | D15: 全新 | E15: 226 | F15: 11 | G15: 留存 | H15: =(E15+F15) -> 237
A16: 龙珠 | B16: 一番赏 | C16: 雅木茶 | D16: 拆摆 | E16: 279 | G16: 留存 | H16: =(E16+F16) -> 279
A17: 龙珠 | B17: 一番赏 | C17: 地球比克 | D17: 拆摆 | E17: 186 | G17: 留存 | H17: =(E17+F17) -> 186
A18: 鬼灭之刃 | B18: Grandista | C18: 善逸 | D18: 全新 | E18: 50 | G18: 留存 | H18: =(E18+F18) -> 50
A19: 龙珠 | B19: 武道会4 | C19: 布玛 | D19: 拆摆 | E19: 560 | G19: 留存 | H19: =(E19+F19) -> 560
A20: 龙珠 | B20: 一番赏 | C20: 胖布欧 | D20: 拆摆 | E20: 700 | G20: 留存 | H20: =(E20+F20) -> 700
A21: 龙珠 | B21: 造型驿传 | C21: 父子摸头 | D21: 全新 | E21: 298 | F21: 20 | G21: 留存 | H21: =(E21+F21) -> 318
A22: 龙珠 | B22: 超像 | C22: 悟空 | D22: 全新 | E22: 500 | G22: 留存 | H22: =(E22+F22) -> 500
A23: 龙珠 | B23: 一番赏 | C23: 地球库林 | D23: 拆摆 | E23: 300 | G23: 留存 | H23: =(E23+F23) -> 300
A24: 龙珠 | B24: 一番赏 | C24: 眼镜悟饭 | D24: 拆摆 | E24: 200 | G24: 留存 | H24: =(E24+F24) -> 200
A25: 龙珠 | B25: 一番赏 | C25: 书包芳芳 | D25: 拆摆 | E25: 100 | G25: 留存 | H25: =(E25+F25) -> 100
A26: 龙珠 | B26: 一番赏 | C26: 贝吉塔大猿 | D26: 拆摆 | E26: 1218 | G26: 卖出 | H26: =(E26+F26) -> 1218 | I26: 1218 | J26: 1179 | K26: =J26-I26 -> -39 | L26: =K26/I26 -> -0.032019704
A27: 龙珠 | B27: Collection | C27: 库林 | D27: 全新 | E27: 85 | G27: 留存 | H27: =(E27+F27) -> 85
A28: 龙珠 | B28: 一番赏 | C28: 野兽悟饭 | D28: 全新 | E28: 120 | G28: 留存 | H28: =(E28+F28) -> 120
A29: 龙珠 | B29: Grandista | C29: 桃红悟空 | D29: 全新 | E29: 120 | G29: 留存 | H29: =(E29+F29) -> 120
A30: 龙珠 | B30: Gxmateria | C30: 弗利萨 | D30: 全新 | E30: 135 | G30: 留存 | H30: =(E30+F30) -> 135
A31: 龙珠 | B31: FiguartsZERO | C31: 超3龙拳 | D31: 全新 | E31: 770 | G31: 留存 | H31: =(E31+F31) -> 770 | M31: 初版
A32: 龙珠 | B32: 武道会2 | C32: 桃白白 | D32: 全新 | E32: 330 | G32: 留存 | H32: =(E32+F32) -> 330
A33: 龙珠 | B33: 一番赏 | C33: 休闲服悟空 | D33: 全新 | E33: 250 | G33: 留存 | H33: =(E33+F33) -> 250
A34: 龙珠 | B34: 一番赏 | C34: 那巴最终赏 | D34: 拆摆 | E34: 166 | G34: 留存 | H34: =(E34+F34) -> 166
A35: 龙珠 | B35: 一番赏 | C35: 红发贝吉塔+小芳 | D35: 全新 | E35: 340 | G35: 留存 | H35: =(E35+F35) -> 340 | M35: set
A36: 龙珠 | B36: 一番赏 | C36: 肌肉沙鲁 | D36: 全新 | E36: 500 | G36: 留存 | H36: =(E36+F36) -> 500
A37: 龙珠 | B37: 必杀技 | C37: 蓝发贝吉塔+扎马斯 | D37: 全新 | E37: 350 | G37: 留存 | H37: =(E37+F37) -> 350
A38: 龙珠 | B38: 必杀技 | C38: 龟派气功孙悟空 | D38: 拆摆 | E38: 180 | G38: 卖出 | H38: =(E38+F38) -> 180 | I38: 180 | J38: 149 | K38: =J38-I38 -> -31 | L38: =K38/I38 -> -0.17222222
A39: 龙珠 | B39: 必杀技 | C39: 贝吉塔 | D39: 全新 | E39: 120 | G39: 留存 | H39: =(E39+F39) -> 120 | M39: 盒损内袋未拆
A40: 龙珠 | B40: BWFC | C40: 军装悟空 | D40: 全新 | E40: 230 | G40: 留存 | H40: =(E40+F40) -> 230
A41: 龙珠 | B41: 一番赏 | C41: 第三任务贝吉特 | D41: 全新 | E41: 145 | G41: 留存 | H41: =(E41+F41) -> 145
A42: 龙珠 | B42: MSP | C42: 超赛孙悟饭 | D42: 全新 | E42: 140 | G42: 留存 | H42: =(E42+F42) -> 140
A43: 龙珠 | B43: 闪耀魅力 | C43: 红衣布尔玛 | D43: 全新 | E43: 223 | G43: 留存 | H43: =(E43+F43) -> 223
A44: 龙珠 | B44: 闪耀魅力 | C44: 雷达布尔玛 | D44: 全新 | E44: 280 | G44: 留存 | H44: =(E44+F44) -> 280
A45: 龙珠 | B45: FES | C45: 14悟空 | D45: 全新 | E45: 70 | G45: 留存 | H45: =(E45+F45) -> 70
A46: 龙珠 | B46: GALS | C46: 军装布尔玛 | D46: 拆摆 | E46: 400 | G46: 留存 | H46: =(E46+F46) -> 400
A47: 龙珠 | B47: Blitzway | C47: 9号胶囊机车 | D47: 全新 | E47: 2000 | F47: 50 | G47: 留存 | H47: =(E47+F47) -> 2050
A48: 龙珠 | B48: GALS | C48: 金发兰琪 | D48: 拆摆 | E48: 460 | G48: 留存 | H48: =(E48+F48) -> 460
A49: 龙珠 | B49: MSP | C49: 贝吉特 | D49: 拆摆 | E49: 460 | G49: 留存 | H49: =(E49+F49) -> 460
A50: 龙珠 | B50: GALS | C50: 比迪丽 | D50: 拆摆 | E50: 150 | G50: 留存 | H50: =(E50+F50) -> 150 | M50: 成色旧，卖
A51: 龙珠 | B51: GALS | C51: 兔女郎布玛 | D51: 拆摆 | E51: 420 | G51: 留存 | H51: =(E51+F51) -> 420
A52: 龙珠 | B52: Blitzway | C52: 机车兰琪 | D52: 全新 | E52: 1865 | G52: 留存 | H52: =(E52+F52) -> 1865
A53: 龙珠 | B53: BWFC | C53: 跳刀特兰克斯 | D53: 拆摆 | E53: 320 | G53: 留存 | H53: =(E53+F53) -> 320
A54: 龙珠 | B54: MSP | C54: 黑发悟空 | D54: 全新 | E54: 210 | G54: 留存 | H54: =(E54+F54) -> 210
A55: 龙珠 | B55: 一番赏 | C55: 蓝发贝吉特+蓝发悟吉塔 | D55: 拆摆 | E55: 960 | G55: 留存 | H55: =(E55+F55) -> 960 | M55: set
A56: 龙珠 | B56: BWFC | C56: 超赛悟空 | D56: 全新 | E56: 210 | G56: 留存 | H56: =(E56+F56) -> 210
A57: 龙珠 | C57: 筋斗云小悟空 | D57: 全新 | E57: 100 | G57: 卖出 | H57: =(E57+F57) -> 100 | I57: 100 | J57: 128 | K57: =(J57-H57) -> 28 | L57: =ROUND(K57/I57,4) -> 0.28 | M57: 红衣
A58: 龙珠 | C58: 筋斗云小悟空 | D58: 全新 | E58: 100 | G58: 留存 | H58: =(E58+F58) -> 100 | M58: 紫衣
A59: 龙珠 | B59: 50th | C59: 超赛悟空 | D59: 全新 | E59: 220 | G59: 留存 | H59: =(E59+F59) -> 220
A60: 龙珠 | B60: 必杀技 | C60: 龟派气功孙悟空 | D60: 全新 | E60: 180 | G60: 留存 | H60: =(E60+F60) -> 180
A61: 龙珠 | B61: 一番赏 | C61: 宇宙服悟空 | D61: 全新 | E61: 230 | G61: 留存 | H61: =(E61+F61) -> 230
A62: 龙珠 | B62: 一番赏 | C62: 丹迪 | D62: 全新 | E62: 320 | G62: 留存 | H62: =(E62+F62) -> 320 | M62: 双封
A63: 龙珠 | B63: CS | C63: 元气斩库林 | D63: 全新 | E63: 2200 | G63: 留存 | H63: =(E63+F63) -> 2200
A64: 龙珠 | B64: 一番赏 | C64: 孙悟饭爷爷 | D64: 全新 | E64: 260 | G64: 留存 | H64: =(E64+F64) -> 260
A65: 龙珠 | B65: 一番赏 | C65: 桃红悟空 | D65: 全新 | E65: 140 | G65: 留存 | H65: =(E65+F65) -> 140
A66: 龙珠 | B66: 一番赏 | C66: 肌肉悟空 | D66: 全新 | E66: 300 | G66: 留存 | H66: =(E66+F66) -> 300
A67: 龙珠 | B67: SMSP | C67: 棍空A赏 | D67: 拆摆 | E67: 770 | G67: 卖出 | H67: =(E67+F67) -> 770 | I67: 770 | J67: 696 | K67: =(J67-I67) -> -74 | L67: =ROUND(K67/I67,4) -> -0.0961 | M67: 无桩
A68: CW | B68: Vibrastar | C68: 井上鸢 | D68: 全新 | E68: 910 | G68: 留存 | H68: =(E68+F68) -> 910
A69: 龙珠 | B69: 一番赏 | C69: 邪念波 | D69: 全新 | E69: 180 | G69: 留存 | H69: =(E69+F69) -> 180
A70: 龙珠 | B70: 一番赏 | C70: 抬头龙1.0 | D70: 拆摆 | E70: 1650 | F70: 30 | G70: 卖出 | H70: =(E70+F70) -> 1680 | I70: =H70 -> 1680 | J70: 1979 | K70: =(J70-I70) -> 299 | L70: =ROUND(K70/I70,4) -> 0.178 | M70: 无盒
A71: 龙珠 | B71: Grandista | C71: 悟天克斯 | D71: 全新 | E71: 128 | G71: 留存 | H71: =(E71+F71) -> 128
A72: 龙珠 | B72: 一番赏 | C72: 龟仙流龟仙人 | D72: 全新 | E72: 260 | G72: 留存 | H72: =(E72+F72) -> 260
A73: 龙珠 | B73: Grandista | C73: 悟吉塔 | D73: 全新 | E73: 165 | G73: 留存 | H73: =(E73+F73) -> 165
A74: 龙珠 | B74: Grandista | C74: 自在极意 | D74: 全新 | E74: 155 | G74: 留存 | H74: =(E74+F74) -> 155
A75: 龙珠 | B75: 一番赏 | C75: 比鲁斯 | D75: 全新 | E75: 270 | G75: 留存 | H75: =(E75+F75) -> 270
A76: 龙珠 | B76: 一番赏 | C76: 一星龙 | D76: 全新 | E76: 220 | G76: 留存 | H76: =(E76+F76) -> 220
A77: 龙珠 | B77: 一番赏 | C77: 肌肉小悟饭 | D77: 全新 | E77: 65 | G77: 留存 | H77: =(E77+F77) -> 65
A78: 奥丁领域 | B78: FLARE | C78: 格温多琳 | D78: 全新 | E78: 500 | F78: 27 | G78: 留存 | H78: =(E78+F78) -> 527
A79: 龙珠 | B79: 一番赏 | C79: 自爆弗利萨 | D79: 全新 | E79: 145 | G79: 留存 | H79: =(E79+F79) -> 145
B80: FuRyu | C80: 红色兔女郎索尼子 | D80: 全新 | E80: 70 | G80: 留存 | H80: =(E80+F80) -> 70
B81: FuRyu | C81: 蓝色兔女郎索尼子 | D81: 全新 | E81: 70 | G81: 留存 | H81: =(E81+F81) -> 70
B82: FuRyu | C82: 黑色兔女郎索尼子 | D82: 全新 | E82: 70 | G82: 留存 | H82: =(E82+F82) -> 70
B83: SEGA | C83: 世界计划多彩舞台 初音未来 | D83: 全新 | E83: 70 | G83: 留存 | H83: =(E83+F83) -> 70 | M83: 卖
A84: 龙珠 | B84: 一番赏 | C84: 激突 超赛悟空 | D84: 全新 | E84: 160 | G84: 留存 | H84: =(E84+F84) -> 160 | M84: 已拆
A85: 龙珠 | B85: 一番赏 | C85: 弗利萨婴儿车 | D85: 全新 | E85: 300 | G85: 留存 | H85: =(E85+F85) -> 300
A86: 龙珠 | B86: 一番赏 | C86: 摩柯不思议 档案馆 | D86: 内袋未拆 | E86: 117 | G86: 留存 | H86: =(E86+F86) -> 117
B87: 大漫匠 | C87: JK兔女郎·卯之樱 | D87: 全新 | E87: 219 | G87: 留存 | H87: =(E87+F87) -> 219 | M87: 卖
A88: 龙珠 | B88: D.O.D | C88: 布欧 | D88: 拆摆 | E88: 600 | G88: 留存 | H88: =(E88+F88) -> 600 | M88: 无盒
A89: 我与机器子 | B89: 眼镜厂 | C89: 机器子 | D89: 全新 | E89: 40 | G89: 留存 | H89: =(E89+F89) -> 40
A90: 我与机器子 | B90: 眼镜厂 | C90: 机器子 | D90: 全新 | E90: 37 | G90: 卖出 | H90: =(E90+F90) -> 37 | M90: 送二狗
A91: 青春期猪头少年不做兔女郎学姐的梦 | B91: ANIPLEX+ | C91: 樱岛麻衣 | D91: 全新 | E91: 560 | G91: 留存 | H91: =(E91+F91) -> 560
A92: 电光超人古立特 | B92: GSC | C92: 宝多六花 | D92: 全新 | E92: 989 | G92: 留存 | H92: =(E92+F92) -> 989
A93: 逆转工作室 | B93: 少女系列 | C93: 林檎 | D93: 全新 | E93: 258 | G93: 留存 | H93: =(E93+F93) -> 258
A94: 龙珠 | B94: 一番赏 | C94: 比克悟饭 | D94: 全新 | E94: 475 | G94: 留存 | H94: =(E94+F94) -> 475
A95: 少女前线 | C95: SSF 索米 | D95: 全新 | E95: 380 | G95: 留存 | H95: =(E95+F95) -> 380
A96: 龙珠 | B96: 超造集 | C96: 比克+库林 | D96: 全新 | E96: 369 | G96: 留存 | H96: =(E96+F96) -> 369
A97: 龙珠 | B97: 一番赏 | C97: 天神 | D97: 全新 | E97: 295 | G97: 留存 | H97: =(E97+F97) -> 295
A98: 龙珠 | B98: Grandista | C98: 黑发常态贝吉塔 | D98: 全新 | E98: 840 | G98: 留存 | H98: =(E98+F98) -> 840
A99: 龙珠 | B99: 一番赏 | C99: 比克VS悟空 | D99: 全新 | E99: 260 | G99: 留存 | H99: =(E99+F99) -> 260
A100: 龙珠 | B100: 一番赏 | C100: 贝吉塔VS悟空 | D100: 全新 | E100: 265 | G100: 留存 | H100: =(E100+F100) -> 265
...

Sheet 泡泡玛特
A1: IP | B1: 系列名称 | C1: 名称 | D1: 买时状态 | E1: 购入价格 | F1: 状态 | G1: 卖出成本 | H1: 卖出价格 | I1: 利润 | J1: 利润率 | K1: 渠道 | L1: 备注
A2: 泡泡玛特 | B2: LABUBU | C2: 大夏日 | D2: 全新 | E2: 498 | F2: 卖出 | G2: 498 | H2: 527 | I2: =H2-G2 -> 29 | J2: =I2/G2 -> 0.058232932 | K2: 京东 | N2: 总花销 | O2: =SUM(E:E) -> 23689
A3: 泡泡玛特 | B3: LABUBU | C3: 象棋国王 | D3: 全新 | E3: 499 | F3: 卖出 | G3: 499 | H3: 676 | I3: =H3-G3 -> 177 | J3: =I3/G3 -> 0.35470942 | K3: 小程序 | N3: 总卖出 | O3: =SUM(H:H) -> 31233
A4: 泡泡玛特 | B4: LABUBU | C4: 象棋国王+皇后 | D4: 全新 | E4: 658 | F4: 卖出 | G4: 658 | H4: 894 | I4: =H4-G4 -> 236 | J4: =I4/G4 -> 0.35866261 | K4: 淘宝 | L4: 胖猪号 | N4: 总卖出成本 | O4: =SUM(G:G) -> 20505
A5: 泡泡玛特 | B5: LABUBU | C5: MOKOKO 甜心挂件 | D5: 全新 | E5: 99 | F5: 卖出 | G5: 99 | H5: 447 | I5: =H5-G5 -> 348 | J5: =I5/G5 -> 3.5151515 | K5: 小程序 | N5: 利润 | O5: =SUM(I:I) -> 10728
A6: 泡泡玛特 | B6: LABUBU | C6: ZIMOMO 大首领 | D6: 全新 | E6: 999 | F6: 卖出 | G6: 999 | H6: 1402 | I6: =H6-G6 -> 403 | J6: =I6/G6 -> 0.4034034 | K6: 小程序 | N6: 利润率 | O6: =ROUND(O5/O4,4) -> 0.5232
A7: 泡泡玛特 | B7: LABUBU | C7: 一代黑皮 | D7: 全新 | E7: 399 | F7: 卖出 | G7: 399 | H7: 466 | I7: =H7-G7 -> 67 | J7: =I7/G7 -> 0.1679198 | K7: 小程序 | N7: 实际支出 | O7: =O2-O3 -> -7544
A8: 泡泡玛特 | B8: LABUBU | C8: 坐坐 | D8: 全新 | E8: 99 | F8: 卖出 | G8: 99 | H8: 105 | I8: =H8-G8 -> 6 | J8: =I8/G8 -> 0.060606061 | K8: 抖音
A9: 泡泡玛特 | B9: LABUBU | C9: 大春野 | D9: 全新 | E9: 499 | F9: 留存 | K9: 小程序
A10: 泡泡玛特 | B10: LABUBU | C10: 象棋皇后 | D10: 全新 | E10: 149 | F10: 留存 | K10: 小程序
A11: 泡泡玛特 | B11: LABUBU | C11: 象棋皇后 | D11: 全新 | E11: 149 | F11: 留存 | K11: 小程序 | L11: 门店
A12: 泡泡玛特 | B12: LABUBU | C12: MOKOKO 甜心 | D12: 全新 | E12: 399 | F12: 卖出 | G12: 399 | H12: 865 | I12: =H12-G12 -> 466 | J12: =I12/G12 -> 1.1679198 | K12: 小程序
A13: 泡泡玛特 | B13: LABUBU | C13: 3.0 | D13: 全新 | E13: 594 | F13: 卖出 | G13: 594 | H13: 944 | I13: =H13-G13 -> 350 | J13: =I13/G13 -> 0.58922559 | K13: 小程序 | L13: 胖猪号，整端
A14: 泡泡玛特 | B14: LABUBU | C14: 坐坐 | D14: 全新 | E14: 594 | F14: 卖出 | G14: 594 | H14: 646 | I14: =H14-G14 -> 52 | J14: =I14/G14 -> 0.087542088 | K14: 小程序 | L14: 整端
A15: 泡泡玛特 | B15: LABUBU | C15: 象棋国王 | D15: 全新 | E15: 499 | F15: 卖出 | K15: 小程序 | L15: 送小孔
A16: 泡泡玛特 | B16: LABUBU | C16: MOKOKO 甜心 | D16: 全新 | E16: 399 | F16: 留存 | K16: 小程序 | L16: 范姐号
A17: 泡泡玛特 | B17: Molly | C17: BabyMolly | D17: 全新 | E17: 474 | F17: 卖出 | G17: 474 | H17: 656 | I17: =H17-G17 -> 182 | J17: =I17/G17 -> 0.38396624 | K17: 淘宝 | L17: 胖猪号
A18: 泡泡玛特 | B18: Molly | C18: BabyMolly | D18: 全新 | E18: 474 | F18: 卖出 | G18: 474 | H18: 695 | I18: =H18-G18 -> 221 | J18: =I18/G18 -> 0.46624473 | K18: 淘宝
A19: 泡泡玛特 | B19: LABUBU | C19: 坐坐 | D19: 全新 | E19: 594 | F19: 卖出 | G19: 592 | H19: 899 | I19: =H19-G19 -> 307 | J19: =I19/G19 -> 0.51858108 | K19: 小程序 | L19: 整端
A20: 泡泡玛特 | B20: LABUBU | C20: 马卡龙 | D20: 全新 | E20: 592 | F20: 卖出 | G20: 592 | H20: 1491 | I20: =H20-G20 -> 899 | J20: =I20/G20 -> 1.5185811 | K20: 小程序 | L20: 整端
A21: 泡泡玛特 | B21: LABUBU | C21: 森林童话 | D21: 全新 | F21: 留存 | K21: 小程序 | L21: 5000积分，自留已拆
A22: 泡泡玛特 | B22: LABUBU | C22: 森林童话 | D22: 全新 | F22: 留存 | K22: 小程序 | L22: 5000积分
A23: 泡泡玛特 | B23: LABUBU | C23: 3.0 | D23: 全新 | E23: 594 | F23: 卖出 | G23: 594 | H23: 1243 | I23: =H23-G23 -> 649 | J23: =I23/G23 -> 1.0925926 | K23: 小程序 | L23: 7月28日，整端
A24: 泡泡玛特 | B24: LABUBU | C24: 3.0 | D24: 全新 | E24: 594 | F24: 卖出 | G24: 594 | H24: 850 | I24: =H24-G24 -> 256 | J24: =I24/G24 -> 0.43097643 | K24: 小程序 | L24: 9月22日，整端
A25: 泡泡玛特 | B25: LABUBU | C25: 可乐 | D25: 全新 | E25: 159 | F25: 卖出 | G25: 159 | H25: 180 | I25: =H25-G25 -> 21 | J25: =I25/G25 -> 0.13207547 | K25: 小程序
A26: 泡泡玛特 | B26: LABUBU | C26: 3.0 | D26: 全新 | E26: 594 | F26: 卖出 | G26: 594 | H26: 1143 | I26: =H26-G26 -> 549 | J26: =I26/G26 -> 0.92424242 | K26: 淘宝 | L26: 胖猪号，整端
A27: 泡泡玛特 | B27: LABUBU | C27: 3.0 | D27: 全新 | E27: 594 | F27: 卖出 | G27: 594 | H27: 1143 | I27: =H27-G27 -> 549 | J27: =I27/G27 -> 0.92424242 | K27: 淘宝 | L27: 胖猪号，整端
A28: 泡泡玛特 | B28: LABUBU | C28: 便利店 | D28: 全新 | E28: 69 | F28: 卖出 | G28: 69 | H28: 107 | I28: =H28-G28 -> 38 | J28: =I28/G28 -> 0.55072464 | K28: 盒机 | L28: 沙拉
A29: 泡泡玛特 | B29: LABUBU | C29: 便利店 | D29: 全新 | E29: 69 | F29: 卖出 | G29: 69 | H29: 70 | I29: =H29-G29 -> 1 | J29: =I29/G29 -> 0.014492754 | K29: 盒机 | L29: 胖猪号，香肠
A30: 泡泡玛特 | B30: SKULL PANDA | C30: 2.0 | D30: 全新 | E30: 1161 | F30: 卖出 | G30: 1161 | H30: 1223 | I30: =H30-G30 -> 62 | J30: =I30/G30 -> 0.053402239 | K30: 淘宝
A31: 泡泡玛特 | B31: LABUBU | C31: 3.0 | D31: 全新 | E31: 594 | F31: 卖出 | G31: 594 | H31: 875 | I31: =H31-G31 -> 281 | J31: =I31/G31 -> 0.47306397 | K31: 小程序 | L31: 胖猪号，9月24日，整端
A32: 泡泡玛特 | B32: LABUBU | C32: 3.0 | D32: 全新 | E32: 594 | F32: 卖出 | G32: 594 | H32: 594 | I32: =H32-G32 -> 0 | J32: =I32/G32 -> 0 | K32: 小程序 | L32: 胖猪号，9月24日
A33: 泡泡玛特 | B33: LABUBU | C33: 马卡龙 | D33: 全新 | E33: 592 | F33: 卖出 | G33: 594 | H33: 1500 | I33: =H33-G33 -> 906 | J33: =I33/G33 -> 1.5252525 | K33: 小程序 | L33: 胖猪号，整端
A34: 泡泡玛特 | B34: LABUBU | C34: 3.0 | D34: 全新 | E34: 99 | F34: 留存 | K34: 盒机 | L34: 爱
A35: 泡泡玛特 | B35: LABUBU | C35: 3.0 | D35: 全新 | E35: 99 | F35: 卖出 | G35: 99 | H35: 134 | I35: =H35-G35 -> 35 | J35: =I35/G35 -> 0.35353535 | K35: 盒机 | L35: 平静
A36: 泡泡玛特 | B36: 米奇家族 | C36: 米妮 | D36: 全新 | E36: 396 | F36: 卖出 | G36: 396 | H36: 359 | I36: =H36-G36 -> -37 | J36: =I36/G36 -> -0.093434343 | K36: 盒机 | L36: 4个
A37: 泡泡玛特 | B37: 米奇家族 | C37: 米奇 | D37: 全新 | E37: 99 | F37: 留存 | K37: 盒机
A38: 泡泡玛特 | B38: 米奇家族 | C38: 高飞 | D38: 全新 | E38: 99 | F38: 留存 | K38: 盒机
A39: 泡泡玛特 | B39: 米奇家族 | C39: 布鲁托 | D39: 全新 | E39: 198 | F39: 卖出 | G39: 198 | H39: 197 | I39: =H39-G39 -> -1 | J39: =I39/G39 -> -0.0050505051 | K39: 盒机 | L39: 2个
A40: 泡泡玛特 | B40: 米奇家族 | C40: 黛西 | D40: 全新 | E40: 99 | F40: 卖出 | G40: 99 | H40: 80 | I40: =H40-G40 -> -19 | J40: =I40/G40 -> -0.19191919 | K40: 盒机
A41: 泡泡玛特 | B41: 米奇家族 | C41: 蒂蒂 | D41: 全新 | E41: 99 | F41: 留存 | K41: 盒机
A42: 泡泡玛特 | B42: LABUBU | C42: 3.0 | D42: 全新 | E42: 99 | F42: 卖出 | G42: 99 | H42: 100 | I42: =H42-G42 -> 1 | J42: =I42/G42 -> 0.01010101 | K42: 盒机 | L42: 忠诚
A43: 泡泡玛特 | B43: LABUBU | C43: 3.0 | D43: 全新 | E43: 99 | F43: 卖出 | G43: 99 | H43: 104 | I43: =H43-G43 -> 5 | J43: =I43/G43 -> 0.050505051 | K43: 盒机 | L43: 爱
A44: 泡泡玛特 | B44: LABUBU | C44: 3.0 | D44: 全新 | E44: 198 | F44: 卖出 | G44: 198 | H44: 214 | I44: =H44-G44 -> 16 | J44: =I44/G44 -> 0.080808081 | K44: 盒机 | L44: 欢乐
A45: 泡泡玛特 | B45: LABUBU | C45: 3.0 | D45: 全新 | E45: 99 | F45: 留存 | K45: 盒机 | L45: 幸运
A46: 泡泡玛特 | B46: LABUBU | C46: 3.0 | D46: 全新 | E46: 99 | F46: 卖出 | G46: 99 | H46: 90 | I46: =H46-G46 -> -9 | J46: =I46/G46 -> -0.090909091 | K46: 盒机 | L46: 平静
A47: 泡泡玛特 | B47: 星星人 | C47: 1.0 | D47: 全新 | E47: 79 | F47: 留存 | K47: 盒机 | L47: 小可爱
A48: 泡泡玛特 | B48: LABUBU | C48: 可乐 | D48: 全新 | E48: 159 | F48: 卖出 | G48: 159 | H48: 180 | I48: =H48-G48 -> 21 | J48: =I48/G48 -> 0.13207547 | K48: 淘宝
A49: 泡泡玛特 | B49: LABUBU | C49: 可乐 | D49: 全新 | E49: 159 | F49: 卖出 | G49: 159 | H49: 179 | I49: =H49-G49 -> 20 | J49: =I49/G49 -> 0.12578616 | K49: 淘宝 | L49: 闷包
A50: 泡泡玛特 | B50: LABUBU | C50: 可乐 | D50: 全新 | E50: 159 | F50: 留存 | K50: 淘宝 | L50: 闷包
A51: 泡泡玛特 | B51: LABUBU | C51: 3.0 | D51: 全新 | E51: 99 | F51: 留存 | K51: 淘宝 | L51: 闷包，忠诚
A52: 泡泡玛特 | B52: LABUBU | C52: 象棋国王 | D52: 全新 | E52: 499 | F52: 留存 | K52: 淘宝
A53: 泡泡玛特 | B53: LABUBU | C53: MOKOKO 夏日 | D53: 全新 | E53: 199 | F53: 卖出 | G53: 199 | H53: 994 | I53: =H53-G53 -> 795 | J53: =I53/G53 -> 3.9949749 | K53: 小程序
A54: 泡泡玛特 | B54: LABUBU | C54: 坐坐 | D54: 全新 | E54: 99 | F54: 卖出 | G54: 99 | H54: 103 | I54: =H54-G54 -> 4 | J54: =I54/G54 -> 0.04040404 | K54: 淘宝 | L54: 闷包
A55: 泡泡玛特 | B55: LABUBU | C55: 心底密码 | D55: 全新 | E55: 79 | F55: 卖出 | G55: 79 | H55: 109 | I55: =H55-G55 -> 30 | J55: =I55/G55 -> 0.37974684 | K55: 盒机 | L55: I
A56: 泡泡玛特 | B56: LABUBU | C56: 前方高能 ROCK | D56: 全新 | E56: 499 | F56: 卖出 | G56: 499 | H56: 497 | I56: =H56-G56 -> -2 | J56: =I56/G56 -> -0.004008016 | K56: 淘宝 | L56: 大娃
A57: 泡泡玛特 | B57: LABUBU | C57: 心底密码 N-Z | D57: 全新 | E57: 1106 | F57: 卖出 | G57: 1106 | H57: 1243 | I57: =H57-G57 -> 137 | J57: =I57/G57 -> 0.1238698 | K57: 小程序 | L57: 整端
A58: 泡泡玛特 | B58: LABUBU | C58: 心底密码 A-M | D58: 全新 | E58: 1106 | F58: 卖出 | G58: 1106 | H58: 1243 | I58: =H58-G58 -> 137 | J58: =I58/G58 -> 0.1238698 | K58: 盒机 | L58: 整端
A59: 泡泡玛特 | B59: LABUBU | C59: 心底密码 A-M | D59: 全新 | E59: 1106 | F59: 卖出 | G59: 1106 | H59: 1160 | I59: =H59-G59 -> 54 | J59: =I59/G59 -> 0.048824593 | K59: 盒机 | L59: 胖猪号，整端
A60: 泡泡玛特 | B60: LABUBU | C60: MOKOKO 毛球派对 | D60: 全新 | E60: 193 | F60: 卖出 | G60: 193 | H60: 1392 | I60: =H60-G60 -> 1199 | J60: =I60/G60 -> 6.2124352 | K60: 小程序
A61: 泡泡玛特 | B61: LABUBU | C61: 可乐 | D61: 全新 | E61: 954 | F61: 卖出 | G61: 954 | H61: 998 | I61: =H61-G61 -> 44 | J61: =I61/G61 -> 0.046121593 | K61: 小程序 | L61: 整端
A62: 泡泡玛特 | B62: 星星人 | C62: 1.0 | D62: 全新 | E62: 474 | F62: 卖出 | G62: 474 | H62: 725 | I62: =H62-G62 -> 251 | J62: =I62/G62 -> 0.52953586 | K62: 小程序 | L62: 整端
A63: 泡泡玛特 | B63: LABUBU | C63: MOKOKO 万圣节 | D63: 全新 | E63: 158 | F63: 留存 | K63: 小程序
A64: 泡泡玛特 | B64: LABUBU | C64: MOKOKO 醒醒春日 | D64: 全新 | E64: 499 | F64: 卖出 | G64: 499 | H64: 1491 | I64: =H64-G64 -> 992 | J64: =I64/G64 -> 1.987976 | K64: 小程序

Sheet 并夕夕
A1: IP | B1: 系列名称 | C1: 名称 | D1: 买时状态 | E1: 状态 | F1: 总价 | G1: 成本价格 | H1: 卖出价格 | I1: 利润 | J1: 利润率 | K1: 备注
A2: 龙珠 | B2: 一番赏 | C2: 地球贝吉塔 | D2: 全新 | E2: 留存 | F2: 301 | M2: 总花销 | N2: =SUM(F:F) -> 24814
A3: 龙珠 | B3: 一番赏 | C3: 界王拳悟空 | D3: 全新 | E3: 留存 | F3: 191 | M3: 总卖出 | N3: =SUM(H:H) -> 365
A4: 龙珠 | B4: 一番赏 | C4: 肌肉特兰克斯 | D4: 全新 | E4: 留存 | F4: 351 | M4: 总卖出成本 | N4: =SUM(G:G) -> 313
A5: 龙珠 | B5: ROS | C5: 特兰克斯 | D5: 全新 | E5: 留存 | F5: 50 | M5: 利润 | N5: =SUM(I:I) -> 52
A6: 龙珠 | B6: 一番赏 | C6: 皮拉夫大王 | D6: 全新 | E6: 留存 | F6: 289 | M6: 利润率 | N6: =ROUND(N5/N4,4) -> 0.1661
A7: 龙珠 | B7: HG | C7: 比克家族 | D7: 全新 | E7: 留存 | F7: 663 | M7: 实际支出 | N7: =N2-N3 -> 24449
A8: 龙珠 | B8: 一番赏 | C8: 小沙鲁 | D8: 全新 | E8: 留存 | F8: 114
A9: 龙珠 | B9: 闪耀魅力 | C9: 比迪丽 | D9: 全新 | E9: 留存 | F9: 82 | K9: B款
A10: 龙珠 | B10: 一番赏 | C10: 桃白白 | D10: 全新 | E10: 留存 | F10: 170
A11: 龙珠 | B11: 一番赏 | C11: 小舞阿修 | D11: 全新 | E11: 留存 | F11: 359
A12: 龙珠 | B12: Grandista | C12: 悟饭 | D12: 全新 | E12: 留存 | F12: 70
A13: 龙珠 | B13: 一番赏 | C13: 比克大魔王 | D13: 全新 | E13: 留存 | F13: 161
A14: 龙珠 | B14: FES | C14: 如意棒小悟空 | D14: 全新 | E14: 留存 | F14: 69 | K14: 9
A15: 龙珠 | B15: Grandista | C15: 漫画色黑发贝吉塔 | D15: 全新 | E15: 留存 | F15: 223
A16: 龙珠 | B16: SMSP | C16: 漫画色超赛悟空 | D16: 全新 | E16: 留存 | F16: 325
A17: 龙珠 | B17: 一番赏 | C17: 机械弗利萨 | D17: 全新 | E17: 留存 | F17: 386
A18: 龙珠 | B18: Grandista | C18: 漫画色超赛贝吉塔 | D18: 全新 | E18: 留存 | F18: 250
A19: 龙珠 | B19: 一番赏 | C19: 库尔德王 | D19: 全新 | E19: 留存 | F19: 502
A20: 龙珠 | B20: 祖国 | C20: 三头胖布欧 | D20: 全新 | E20: 留存 | F20: 124 | K20: 6头，卖
A21: 龙珠 | B21: 祖国 | C21: 4形态弗利萨 | D21: 全新 | E21: 留存 | F21: 45 | K21: 卖
A22: 龙珠 | B22: Collection | C22: 琪琪 | D22: 全新 | E22: 留存 | F22: 62
A23: 龙珠 | B23: 五月人形 | C23: 盔甲小悟空 | D23: 全新 | E23: 留存 | F23: 87
A24: 鬼灭之刃 | B24: Grandista | C24: 炭治郎 | D24: 全新 | E24: 留存 | F24: 45
A25: 鬼灭之刃 | B25: Grandista | C25: 伊之助 | D25: 全新 | E25: 留存 | F25: 69
A26: 龙珠 | B26: Gxmateria | C26: 贝吉塔 | D26: 全新 | E26: 留存 | F26: 61
A27: 龙珠 | B27: Gxmateria | C27: 气功波悟饭 | D27: 全新 | E27: 留存 | F27: 56
A28: 龙珠 | B28: 历史盒子 | C28: 小悟空 | D28: 全新 | E28: 留存 | F28: 61
A29: 龙珠 | B29: 历史盒子 | C29: 巴达克 | D29: 全新 | E29: 留存 | F29: 67
A30: 龙珠 | B30: 历史盒子 | C30: 超赛悟空 | D30: 全新 | E30: 留存 | F30: 78
A31: 龙珠 | B31: SMSD | C31: 爆气悟空 | D31: 全新 | E31: 留存 | F31: 201
A32: 龙珠 | B32: Grandista | C32: 黑悟空 | D32: 全新 | E32: 留存 | F32: 100
A33: 龙珠 | B33: 闪耀魅力 | C33: 人造人18号 | D33: 全新 | E33: 留存 | F33: 227 | K33: 蓝衣白裤弯腰
A34: 龙珠 | B34: SMSP | C34: 黑发悟吉塔 | D34: 全新 | E34: 留存 | F34: 238
A35: 龙珠 | B35: BWFC | C35: 人造人17号 | D35: 全新 | E35: 留存 | F35: 92
A36: 龙珠 | B36: 闪耀魅力 | C36: 人造人18号 | D36: 全新 | E36: 留存 | F36: 82 | K36: 站姿
A37: 龙珠 | B37: 闪耀魅力 | C37: 机枪兰琪 | D37: 全新 | E37: 留存 | F37: 260 | K37: 绿色
A38: 龙珠 | B38: SMSP | C38: 超4悟空04色 | D38: 全新 | E38: 留存 | F38: 388 | K38: 蹲姿
A39: 龙珠 | B39: 燃烧的战士 | C39: 贝吉塔 | D39: 全新 | E39: 留存 | F39: 54
A40: 龙珠 | B40: Gxmateria | C40: 踩波悟空 | D40: 全新 | E40: 留存 | F40: 66
A41: 龙珠 | B41: SMSP | C41: 蹲姿巴达克04色 | D41: 全新 | E41: 留存 | F41: 138
A42: 龙珠 | B42: SMSP | C42: 蹲姿巴达克03色 | D42: 全新 | E42: 卖出 | F42: 138 | G42: =F42 -> 138 | H42: 175 | I42: =H42-G42 -> 37 | J42: =I42/G42 -> 0.26811594
A43: 龙王的工作 | B43: Alter | C43: 空银子 | D43: 全新 | E43: 留存 | F43: 359
A44: 青春期猪头少年不做兔女郎学姐的梦 | B44: Taito | C44: 樱岛麻衣 | D44: 全新 | E44: 留存 | F44: 132
A45: 龙珠 | B45: 一番赏 | C45: 人造人16号 | D45: 全新 | E45: 留存 | F45: 185
A46: 龙珠 | B46: 一番赏 | C46: 人造人17号 | D46: 全新 | E46: 留存 | F46: 233
A47: 龙珠 | B47: 一番赏 | C47: 人造人18号 | D47: 全新 | E47: 留存 | F47: 233
A48: 龙珠 | B48: 一番赏 | C48: 人造人19号 | D48: 全新 | E48: 留存 | F48: 636
A49: 龙珠 | B49: 一番赏 | C49: 人造人20号 | D49: 全新 | E49: 留存 | F49: 593
A50: 龙珠 | B50: 一番赏 | C50: 黄金弗利萨 | D50: 全新 | E50: 留存 | F50: 202 | K50: 压盒
A51: 龙珠 | B51: 一番赏 | C51: 完全体沙鲁 | D51: 全新 | E51: 留存 | F51: 360 | K51: 已拆
A52: 龙珠 | B52: 一番赏 | C52: 棍子小悟空 | D52: 全新 | E52: 留存 | F52: 185 | K52: 已拆
A53: 龙珠 | B53: 一番赏 | C53: 地球悟饭 | D53: 全新 | E53: 留存 | F53: 214
A54: 龙珠 | B54: 一番赏 | C54: 父子抱A赏 | D54: 全新 | E54: 留存 | F54: 358
A55: 龙珠 | B55: 一番赏 | C55: 沙鲁一形态 | D55: 全新 | E55: 留存 | F55: 328 | K55: 压盒
A56: 龙珠 | B56: 一番赏 | C56: 地球龟仙人 | D56: 全新 | E56: 留存 | F56: 358
A57: 龙珠 | B57: 一番赏 | C57: 地球天津饭 | D57: 全新 | E57: 留存 | F57: 366
A58: 龙珠 | B58: 一番赏 | C58: 地球饺子 | D58: 全新 | E58: 留存 | F58: 285
A59: 龙珠 | B59: MSP | C59: 常态特兰克斯 | D59: 全新 | E59: 留存 | F59: 196
A60: 龙珠 | B60: 一番赏 | C60: 达列斯 | D60: 全新 | E60: 留存 | F60: 351
A61: 龙珠 | B61: 一番赏 | C61: L赏布罗利 | D61: 全新 | E61: 留存 | F61: 389
A62: 龙珠 | B62: 一番赏 | C62: 肥龙D赏布罗利 | D62: 全新 | E62: 留存 | F62: 475
A63: 龙珠 | B63: SMSP | C63: 蹲姿巴达克03色 | D63: 全新 | E63: 留存 | F63: 180
A64: 龙珠 | B64: LC | C64: 悟天克斯 | D64: 全新 | E64: 留存 | F64: 83
A65: 龙珠 | B65: SMSP | C65: 蹲姿巴达克01色 | D65: 全新 | E65: 留存 | F65: 137
A66: 龙珠 | B66: Grandista | C66: nero巴达克 | D66: 全新 | E66: 留存 | F66: 136
A67: 龙珠 | B67: Gxmateria | C67: 元气斩库林 | D67: 全新 | E67: 留存 | F67: 64
... A70: 龙珠 | B70: Gxmateria | C70: 悟天克斯 | D70: 全新 | E70: 留存 | F70: 155
A71: 龙珠 | B71: 祖国 | C71: 超3 | D71: 全新 | E71: 留存 | F71: 44 | K71: 卖
A72: 龙珠 | B72: 一番赏 | C72: 宇宙服库林 | D72: 全新 | E72: 卖出 | F72: 175 | G72: 175 | H72: 190 | I72: =H72-G72 -> 15 | J72: =I72/G72 -> 0.085714286 | K72: 已拆
A73: 龙珠 | B73: Gxmateria | C73: 人造人16号 | D73: 全新 | E73: 留存 | F73: 65
A74: 龙珠 | B74: FiguartsZERO | C74: 特兰克斯vs弗利萨 | D74: 全新 | E74: 留存 | F74: 850
A75: 龙珠 | B75: 一番赏 | C75: 地球套 档案馆 | D75: 全新 | E75: 留存 | F75: 116
A76: 龙珠 | B76: BOS | C76: 悟天克斯 | D76: 全新 | E76: 留存 | F76: 82
A77: 龙珠 | B77: SHF | C77: 布尔玛 | D77: 全新 | E77: 留存 | F77: 292
A78: 命运-冠位指定 | B78: Stronger | C78: 玛修 | D78: 全新 | E78: 留存 | F78: 475 | K78: 限定版
A79: 原创 | B79: Otherwhere | C79: 辛西娅 | D79: 全新 | E79: 留存 | F79: 402
A80: 龙珠 | B80: Grandista | C80: 悟空发波 | D80: 全新 | E80: 留存 | F80: 70
A81: 龙珠 | B81: 一番赏 | C81: 布尔玛照镜子 | D81: 全新 | E81: 留存 | F81: 54 | K81: 无盒散货
A82: 龙珠 | B82: Grandista | C82: 达列斯 | D82: 全新 | E82: 留存 | F82: 47
A83: 龙珠 | B83: 一番赏 | C83: 悟天克斯鬼魂 | D83: 全新 | E83: 留存 | F83: 176
A84: 碧蓝航线 | B84: Alphamax | C84: 大凤 插画版 | D84: 全新 | E84: 留存 | F84: 1225
A85: 龙珠 | B85: 一番赏 | C85: 乌龙 神龙 | D85: 全新 | E85: 留存 | F85: 205
A86: 龙珠 | B86: 一番赏 | C86: last 孙悟饭&悟空 | D86: 全新 | E86: 留存 | F86: 394
A87: rurudo | B87: Pink Charm | C87: 伊芙 | D87: 全新 | E87: 留存 | F87: 1357
A88: 龙珠 | B88: 一番赏 | C88: 战损贝吉塔 | D88: 全新 | E88: 留存 | F88: 664
A89: 碧蓝航线 | B89: Alter | C89: 大凤 放学后的甜蜜时光 | D89: 全新 | E89: 留存 | F89: 1340 | K89: 特典版
A90: 龙珠 | B90: 一番赏 | C90: 40周年 再见悟空 | D90: 全新 | E90: 留存 | F90: 396 | K90: B赏
A91: 龙珠 | B91: 一番赏 | C91: 40周年 悟空骑龙 | D91: 全新 | E91: 留存 | F91: 711 | K91: A赏
B92: ACEmodeling | C92: 人妻奈奈 | D92: 全新 | E92: 留存 | F92: 76
A93: 龙珠 | B93: 竞争对手 | C93: 18号&撒旦 | D93: 全新 | E93: 留存 | F93: 62
A94: 龙珠 | B94: Grandista | C94: 魔人贝吉塔 | D94: 全新 | E94: 留存 | F94: 81
A95: 魔法少女小圆 | B95: GSC | C95: 恶魔小焰 | D95: 全新 | E95: 留存 | F95: 719
A96: 龙珠 | B96: 拼奇 | C96: 天下第一武道会 | D96: 全新 | E96: 留存 | F96: 57
A97: 龙珠 | B97: 一番赏 | C97: 40周年 马克杯 | D97: 全新 | E97: 留存 | F97: 68 | K97: 两个

Sheet 预定
A1: IP | B1: 系列名称 | C1: 名称 | D1: 定金 | E1: 尾款 | F1: 运费 | G1: 状态 | H1: 总价 | I1: 卖出成本 | J1: 卖出价格 | K1: 利润 | L1: 利润率 | M1: 途径 | N1: 备注
A2: 龙珠 | B2: BOS | C2: 超3悟天克斯 | D2: 10 | G2: 卖出 | H2: =D2+E2+F2 -> 10 | I2: 10 | J2: 0 | K2: =J2-I2 -> -10 | L2: =ROUND(K2/I2,4) -> -1 | M2: 淘宝一诺 | N2: 弃单 | P2: 总花销 | Q2: =SUM(H:H) -> 96642
A3: 龙珠 | B3: HG | C3: 人造人 | D3: 81 | E3: 668 | G3: 留存 | H3: =D3+E3+F3 -> 749 | M3: 指乐无穷 | N3: 24年2月 | P3: 总卖出 | Q3: =SUM(J:J) -> 19270
A4: 海贼王 | B4: 桌面系列 | C4: 路飞全形态 | D4: 34 | E4: 409 | G4: 留存 | H4: =D4+E4+F4 -> 443 | M4: 指乐无穷 | N4: 24年3月，一坨 | P4: 总卖出成本 | Q4: =SUM(I:I) -> 18628
A5: 龙珠 | B5: PLEX | C5: 变身萨博 | D5: 333 | E5: 1428 | G5: 卖出 | H5: =D5+E5+F5 -> 1761 | I5: 1761 | J5: 1846 | K5: =J5-I5 -> 85 | L5: =ROUND(K5/I5,4) -> 0.0483 | M5: 指乐无穷 | N5: 24年2月 | P5: 利润 | Q5: =SUM(K:K) -> 642
A6: 龙珠 | B6: PLEX | C6: 萨博 | D6: 284 | E6: 1415 | F6: 16 | G6: 留存 | H6: =D6+E6+F6 -> 1715 | M6: 淘宝华宝 | N6: 24年1月 | P6: 利润率 | Q6: =ROUND(Q5/Q4,4) -> 0.0345
A7: 龙珠 | B7: PLEX | C7: 多多利亚 | D7: 299 | E7: 1395 | G7: 卖出 | H7: =D7+E7+F7 -> 1694 | I7: 1694 | J7: 1760 | K7: =J7-I7 -> 66 | L7: =ROUND(K7/I7,4) -> 0.039 | M7: 指乐无穷 | N7: 24年4月 | P7: 实际支出 | Q7: =Q2-Q3 -> 77372
A8: 龙珠 | B8: SHF | C8: 9号胶囊机车 | D8: 46 | E8: 410 | G8: 留存 | H8: =D8+E8+F8 -> 456 | M8: 指乐无穷 | N8: 24年4月
A9: 龙珠 | B9: PLEX | C9: 多多利亚 | D9: 295 | E9: 1438 | G9: 留存 | H9: =D9+E9+F9 -> 1733 | M9: 淘宝华宝 | N9: 24年4月
A10: 龙珠 | B10: 出阵 | C10: 基纽特战队 | D10: 76 | E10: 360 | G10: 留存 | H10: =D10+E10+F10 -> 436 | M10: 塑唐 | N10: 24年7月
A11: 啦啦队系列 | B11: Hobby·sakura | C11: 美沙纪 | D11: 70 | E11: 504 | G11: 卖出 | H11: =D11+E11+F11 -> 574 | I11: 574 | J11: 520 | K11: =J11-I11 -> -54 | L11: =ROUND(K11/I11,4) -> -0.0941 | M11: 咸鱼 | N11: 24年7月
A12: 啦啦队系列 | B12: Hobby·sakura | C12: 美沙纪 | D12: 192 | E12: 436 | G12: 留存 | H12: =D12+E12+F12 -> 628 | N12: 24年7月
A13: 龙珠 | C13: 鸟山明玩大便 | D13: 450 | E13: 0 | F13: 18 | G13: 留存 | H13: =D13+E13+F13 -> 468 | M13: 咸鱼 | N13: 手艺人自制
A14: 街霸 | B14: Max Factory | C14: 春丽 | D14: 245 | E14: 1700 | F14: 18 | G14: 留存 | H14: =D14+E14+F14 -> 1963 | M14: 模玩熊 | N14: 24年7月
A15: 龙珠 | B15: 桌面系列 | C15: 父子机车 | D15: 46 | E15: 1250 | G15: 留存 | H15: =D15+E15+F15 -> 1296 | M15: 塑唐
A16: 遗孀之雪女 | B16: PURE | C16: 雪乃深冬 | D16: 248 | E16: 650 | G16: 留存 | H16: =D16+E16+F16 -> 898 | M16: Hobby Heaven | N16: 24年9月
A17: 间谍过家家 | B17: GK | C17: 婴儿车阿尼亚 | D17: 173 | E17: 290 | G17: 卖出 | H17: =D17+E17+F17 -> 463 | I17: 463 | J17: 437 | K17: =J17-I17 -> -26 | L17: =ROUND(K17/I17,4) -> -0.0562 | M17: 淘宝 | N17: 24年3季度末
A18: CW | B18: Vibrastar | C18: 修女 | D18: 150 | E18: 904 | G18: 卖出 | H18: =D18+E18+F18 -> 1054 | I18: 1054 | J18: 1053 | K18: =J18-I18 -> -1 | L18: =ROUND(K18/I18,4) -> -0.0009 | M18: 橘子屋 | N18: 24年10月
A19: 东方Project | B19: APEX-TOYS | C19: 蕾米莉亚 | D19: 146 | E19: 967 | G19: 留存 | H19: =D19+E19+F19 -> 1113 | M19: 淘宝叔叔 | N19: 24年10月
A20: 啦啦队系列 | B20: Hobby·sakura | C20: 莉库 | D20: 123 | E20: 488 | G20: 留存 | H20: =D20+E20+F20 -> 611 | M20: 淘宝叔叔 | N20: 24年11月
A21: 原创 | B21: Hobby·sakura | C21: 不良女警 | D21: 107 | E21: 691 | G21: 留存 | H21: =D21+E21+F21 -> 798 | M21: 淘宝叔叔 | N21: 24年11月，卖
A22: 神明渴望游戏。 | B22: elCOCO | C22: 帕尔 | D22: 30 | E22: 131 | G22: 留存 | H22: =D22+E22+F22 -> 161 | M22: 指乐无穷 | N22: 24年11月，卖
A23: 沙漠大冒险 | B23: 桌面系列 | C23: 104战车 | D23: 278 | E23: 1217 | G23: 留存 | H23: =D23+E23+F23 -> 1495 | M23: 指乐无穷 | N23: 24年11月
A24: 无职转生 | B24: Mega House | C24: 艾莉丝 | D24: 40 | E24: 383 | G24: 留存 | H24: =D24+E24+F24 -> 423 | M24: 淘宝叔叔 | N24: 24年11月
A25: 无职转生 | B25: 寿屋 | C25: 艾莉丝 | D25: 106 | E25: 591 | G25: 留存 | H25: =D25+E25+F25 -> 697 | M25: 叔叔会员购 | N25: 24年12月
A26: 无职转生 | B26: 寿屋 | C26: 艾莉丝 | D26: 60 | E26: 566 | G26: 卖出 | H26: =D26+E26+F26 -> 626 | I26: 626 | J26: 538 | K26: =J26-I26 -> -88 | L26: =ROUND(K26/I26,4) -> -0.1406 | M26: 淘宝叔叔 | N26: 25年1月
A27: 更衣人偶坠入爱河 | B27: Taito | C27: 喜多川海梦 利兹 | D27: 22 | E27: 65 | F27: 8 | G27: 留存 | H27: =D27+E27+F27 -> 95 | M27: 淘宝Hpoi | N27: 24年12月
A28: 龙珠 | B28: FiguartsZERO | C28: 超级赛亚人2孙悟饭-汹涌的实力 | D28: 103 | E28: 474 | G28: 留存 | H28: =D28+E28+F28 -> 577 | M28: 叔叔会员购 | N28: 24年12月
A29: 青春恋爱物语 | B29: GSC | C29: 雪乃 | D29: 121 | E29: 665 | G29: 留存 | H29: =D29+E29+F29 -> 786 | M29: 淘宝叔叔 | N29: 24年12月
A30: SIKI ANIM | C30: 阿尔维娜 | D30: 50 | E30: 248 | G30: 留存 | H30: =D30+E30+F30 -> 298 | M30: 淘宝Hpoi | N30: 25年1月，卖
A31: 龙珠 | B31: HG | C31: 皮拉夫三人组 | D31: 130 | E31: 581 | G31: 留存 | H31: =D31+E31+F31 -> 711 | M31: 指乐无穷 | N31: 25年2月
A32: 东方Project | B32: MAGI ARTS | C32: 十六夜咲夜 | D32: 165 | E32: 822 | G32: 留存 | H32: =D32+E32+F32 -> 987 | M32: 叔叔会员购 | N32: 25年2月，卖
A33: 魔女之旅 | B33: Taito | C33: 伊蕾娜 | D33: 22 | E33: 75 | G33: 留存 | H33: =D33+E33+F33 -> 97 | M33: 淘宝Hpoi | N33: 25年3月
A34: 黑岩射手 | B34: GSC | C34: 狂化黑岩射手 | D34: 99 | E34: 747 | G34: 留存 | H34: =D34+E34+F34 -> 846 | M34: GSC小程序 | N34: 25年3月
A35: 黑岩射手 | B35: GSC | C35: 狂化黑岩射手 | D35: 90 | E35: 747 | G35: 卖出 | H35: =D35+E35+F35 -> 837 | I35: 837 | J35: 777 | K35: =J35-I35 -> -60 | L35: =ROUND(K35/I35,4) -> -0.0717 | M35: GSC小程序 | N35: 25年3月
A36: 黑岩射手 | B36: GSC | C36: 狂化黑岩射手 | D36: 100 | E36: 747 | G36: 留存 | H36: =D36+E36+F36 -> 847 | M36: GSC小程序 | N36: 25年3月，卖
B37: OMAHA | C37: 波妮塔酱 | D37: 200 | E37: 696 | G37: 留存 | H37: =D37+E37+F37 -> 896 | M37: 淘宝橘子屋 | N37: 25年4月
A38: 龙珠 | B38: 桌面系列 | C38: 超赛父子机车 | D38: 94 | E38: 1085 | G38: 留存 | H38: =D38+E38+F38 -> 1179 | M38: 塑唐 | N38: 25年4月
A39: 命运石之门 | B39: WAVE | C39: 牧濑红莉栖 | D39: 120 | E39: 522 | G39: 卖出 | H39: =D39+E39+F39 -> 642 | I39: 642 | J39: 764 | K39: =J39-I39 -> 122 | L39: =ROUND(K39/I39,4) -> 0.19 | M39: 淘宝Hpoi | N39: 25年4月
A40: 约会大作战 | B40: Taito | C40: 时崎狂三 | D40: 22 | E40: 72 | G40: 留存 | H40: =D40+E40+F40 -> 94 | M40: 淘宝Hpoi | N40: 25年4月
A41: Fate/Zero | B41: GSC | C41: 风王骑兵 | D41: 85 | E41: 799 | G41: 留存 | H41: =D41+E41+F41 -> 884 | M41: GSC小程序 | N41: 25年4月
A42: 更衣人偶坠入爱河 | B42: Taito | C42: 喜多川海梦 黑江雫 | D42: 20 | E42: 75 | G42: 留存 | H42: =D42+E42+F42 -> 95 | M42: 淘宝Hpoi | N42: 25年5月
A43: 龙珠 | B43: Grandista | C43: 贝吉塔 | D43: 96 | E43: 0 | G43: 留存 | H43: =D43+E43+F43 -> 96 | M43: 指乐无穷 | N43: 25年5月
A44: 龙珠 | B44: PLEX | C44: 自爆沙鲁 | D44: 385 | E44: 1653 | G44: 留存 | H44: =D44+E44+F44 -> 2038 | M44: 淘宝华宝 | N44: 25年5月
A45: 更衣人偶坠入爱河 | B45: Alter | C45: 喜多川海梦 利兹 | D45: 196 | E45: 909 | G45: 留存 | H45: =D45+E45+F45 -> 1105 | M45: 叔叔会员购 | N45: 25年5月
A46: 狂赌之渊 | B46: 寿屋 | C46: 蛇喰梦子 | D46: 80 | E46: 513 | G46: 卖出 | H46: =D46+E46+F46 -> 593 | I46: 593 | J46: 626 | K46: =J46-I46 -> 33 | L46: =ROUND(K46/I46,4) -> 0.0556 | M46: 淘宝Hpoi | N46: 25年5月
A47: 未来日记 | B47: GSC POP UP | C47: 我妻由乃 | D47: 45 | E47: 149 | G47: 留存 | H47: =D47+E47+F47 -> 194 | M47: 指乐无穷 | N47: 25年5月，普通版
A48: 未来日记 | B48: GSC POP UP | C48: 我妻由乃 | D48: 45 | E48: 204 | G48: 留存 | H48: =D48+E48+F48 -> 249 | M48: GSC小程序 | N48: 25年5月，特别版
A49: 龙珠 | B49: FiguartsZERO | C49: 孙悟空布尔玛 | D49: 128 | E49: 632 | G49: 留存 | H49: =D49+E49+F49 -> 760 | M49: 叔叔会员购 | N49: 25年6月
A50: 电光超人古立特 | B50: 寿屋 | C50: 宝多六花 | D50: 95 | E50: 541 | G50: 留存 | H50: =D50+E50+F50 -> 636 | M50: 淘宝Hpoi | N50: 25年6月
A51: 明日方舟 | B51: Alter | C51: 噩兆 | D51: 440 | E51: 1666 | G51: 留存 | H51: =D51+E51+F51 -> 2106 | M51: 淘宝明日方舟 | N51: 25年6月，卖
A52: 无职转生 | B52: 寿屋 | C52: 洛琪希 | D52: 799 | E52: 0 | G52: 留存 | H52: =D52+E52+F52 -> 799 | M52: 拼多多 | N52: 25年6月，特别版，卖
A53: 尼尔自动人形 | B53: GSC | C53: 2B | D53: 120 | E53: 600 | G53: 留存 | H53: =D53+E53+F53 -> 720 | M53: 淘宝Hpoi | N53: 25年6月
A54: 败犬女主太多了 | B54: GSC POP UP | C54: 八奈见杏菜 | D54: 59 | E54: 133 | G54: 留存 | H54: =D54+E54+F54 -> 192 | M54: 叔叔会员购 | N54: 25年7月
A55: 败犬女主太多了 | B55: GSC POP UP | C55: 八奈见杏菜 | D55: 59 | E55: 253 | G55: 卖出 | H55: =D55+E55+F55 -> 312 | I55: 312 | J55: 328 | K55: =J55-I55 -> 16 | L55: =ROUND(K55/I55,4) -> 0.0513 | M55: 叔叔会员购 | N55: 25年7月，卖
A56: 碧蓝航线 | B56: Alter | C56: 柴郡 | D56: 219 | E56: 0 | G56: 卖出 | H56: =D56+E56+F56 -> 219 | I56: 219 | J56: 0 | K56: =J56-I56 -> -219 | L56: =ROUND(K56/I56,4) -> -1 | M56: 叔叔会员购 | N56: 弃单
A57: CW | B57: Vibrastar | C57: 亚子 | D57: 200 | E57: 805 | G57: 留存 | H57: =D57+E57+F57 -> 1005 | M57: 橘子屋 | N57: 25年7月
A58: 拳皇 | B58: 否极 | C58: 不知火舞 | D58: 150 | E58: 791 | G58: 卖出 | H58: =D58+E58+F58 -> 941 | I58: 941 | J58: 875 | K58: =J58-I58 -> -66 | L58: =ROUND(K58/I58,4) -> -0.0701 | M58: 叔叔会员购 | N58: 25年9月
A59: 东方Project | B59: MAGI ARTS | C59: 古明地恋 | D59: 165 | E59: 876 | G59: 卖出 | H59: =D59+E59+F59 -> 1041 | I59: 1041 | J59: 1391 | K59: =J59-I59 -> 350 | L59: =ROUND(K59/I59,4) -> 0.3362 | M59: 叔叔会员购 | N59: 25年7月
A60: EVA | B60: Alter | C60: 明日香 | D60: 188 | E60: 955 | G60: 留存 | H60: =D60+E60+F60 -> 1143 | M60: 叔叔会员购 | N60: 25年8月
A61: 龙珠 | B61: PLEX | C61: 比克 | D61: 288 | E61: 1280 | G61: 留存 | H61: =D61+E61+F61 -> 1568 | M61: 指乐无穷 | N61: 25年9月
A62: 蔚蓝档案 | B62: GSC | C62: 圣园未花 | D62: 156 | E62: 779 | G62: 留存 | H62: =D62+E62+F62 -> 935 | M62: 叔叔会员购 | N62: 25年9月
A63: 龙珠 | B63: SHF | C63: 孙悟空与龙-龙珠40周年纪念款 | D63: 195 | E63: 441 | F63: 22 | G63: 留存 | H63: =D63+E63+F63 -> 658 | M63: 圣之缘 | N63: 25年9月
A64: 命运石之门 | B64: GSC | C64: 魔眼 | D64: 67 | E64: 1136 | G64: 卖出 | H64: =D64+E64+F64 -> 1203 | I64: 1203 | J64: 1670 | K64: =J64-I64 -> 467 | L64: =ROUND(K64/I64,4) -> 0.3882 | M64: 淘宝叔叔 | N64: 25年6月
A65: 命运石之门 | B65: GSC | C65: 魔眼 | D65: 67 | E65: 1136 | G65: 卖出 | H65: =D65+E65+F65 -> 1203 | I65: 1203 | J65: 1681 | K65: =J65-I65 -> 478 | L65: =ROUND(K65/I65,4) -> 0.3973 | M65: 淘宝叔叔 | N65: 25年6月
A66: 命运石之门 | B66: GSC | C66: 魔眼 | D66: 67 | E66: 1136 | G66: 留存 | H66: =D66+E66+F66 -> 1203 | M66: 淘宝叔叔 | N66: 25年6月
A67: 火影忍者 | B67: FiguartsZERO | C67: 漩涡鸣人 | D67: 57 | E67: 544 | G67: 留存 | H67: =D67+E67+F67 -> 601 | M67: 塑唐 | N67: 25年9月，火影忍者72册漫画封面系列
A68: 期待在地下城邂逅有错吗 | B68: 寿屋 | C68: 剑姬神圣谭 | D68: 650 | E68: 0 | G68: 留存 | H68: =D68+E68+F68 -> 650 | M68: 拼多多 | N68: 25年8月，卖，赔偿50
A69: 龙珠 | B69: PLEX | C69: 巴达克大猿 | D69: 349 | E69: 1318 | G69: 留存 | H69: =D69+E69+F69 -> 1667 | M69: 撸撸的模型店 | N69: 25年8月
A70: 蔚蓝档案 | B70: GSC | C70: 狐坂若藻 | D70: 285 | E70: 769 | G70: 留存 | H70: =D70+E70+F70 -> 1054 | M70: 指乐无穷 | N70: 25年8月，卖
A71: 街霸 | B71: Max Factory | C71: 春丽 | D71: 200 | E71: 867 | G71: 留存 | H71: =D71+E71+F71 -> 1067 | M71: 叔叔会员购 | N71: 25年10月
A72: 碧蓝航线 | B72: APEX-TOYS | C72: 尾张 | D72: 130 | E72: 677 | G72: 留存 | H72: =D72+E72+F72 -> 807 | M72: 叔叔会员购 | N72: 25年10月
A73: 无职转生 | B73: Mega House | C73: 洛琪希 | D73: 421 | E73: 0 | G73: 留存 | H73: =D73+E73+F73 -> 421 | M73: 抖音叔叔 | N73: 25年10月
A74: 龙珠 | B74: PLEX | C74: 巨猿 托马 | D74: 395 | E74: 1369 | G74: 卖出 | H74: =D74+E74+F74 -> 1764 | I74: 1764 | J74: 1690 | K74: =J74-I74 -> -74 | L74: =ROUND(K74/I74,4) -> -0.042 | M74: 撸撸的模型店 | N74: 25年12月
A75: 原创 | B75: Bibi Buttons | C75: 审讯官 | D75: 105 | E75: 447 | G75: 留存 | H75: =D75+E75+F75 -> 552 | M75: 叔叔会员购 | N75: 25年12月
A76: 原创 | B76: Bibi Buttons | C76: 审讯官 | D76: 105 | E76: 533 | G76: 卖出 | H76: =D76+E76+F76 -> 638 | I76: 638 | J76: 586 | K76: =J76-I76 -> -52 | L76: =ROUND(K76/I76,4) -> -0.0815 | M76: 叔叔会员购 | N76: 25年12月
B77: 尺玉 | C77: 雪乃深冬 | D77: 115 | E77: 568 | G77: 卖出 | H77: =D77+E77+F77 -> 683 | I77: 683 | J77: 596 | K77: =J77-I77 -> -87 | L77: =ROUND(K77/I77,4) -> -0.1274 | M77: 叔叔会员购 | N77: 25年12月
A78: 战双：帕弥什 | B78: 良笑塑美 | C78: 露西亚·深红囚影 | D78: 169 | E78: 860 | G78: 卖出 | H78: =D78+E78+F78 -> 1029 | I78: 1029 | J78: 939 | K78: =J78-I78 -> -90 | L78: =ROUND(K78/I78,4) -> -0.0875 | M78: 叔叔会员购 | N78: 25年11月，含特典
A79: 数码宝贝 | B79: Mega House | C79: 战斗暴龙兽再版 | D79: 167 | E79: 846 | G79: 留存 | H79: =D79+E79+F79 -> 1013 | M79: 猫受屋 | N79: 26年1月
A80: 无职转生 | B80: Mega House | C80: 希露菲 | D80: 35 | E80: 336 | G80: 留存 | H80: =D80+E80+F80 -> 371 | M80: 猫受屋 | N80: 26年1月
A81: Fate/stay night | B81: GSC | C81: 阿尔托莉雅 Alter huke 联名套装 | D81: 160 | E81: 1109 | G81: 卖出 | H81: =D81+E81+F81 -> 1269 | I81: 1269 | J81: 1193 | K81: =J81-I81 -> -76 | L81: =ROUND(K81/I81,4) -> -0.0599 | M81: GSC小程序 | N81: 26年1月
A82: CARNEADES | B82: WAVE | C82: 伊芙 | D82: 284 | E82: 1006 | G82: 留存 | H82: =D82+E82+F82 -> 1290 | M82: 猫受屋 | N82: 26年1月
A83: 初音未来 | B83: GSC | C83: 初音未来 15周年纪念 粘土人 | D83: 42 | E83: 396 | G83: 留存 | H83: =D83+E83+F83 -> 438 | M83: GSC小程序 | N83: 26年1月
A84: 龙珠 | B84: Mega House | C84: 龙珠Z 03 布尔玛 | D84: 372 | E84: 0 | G84: 留存 | H84: =D84+E84+F84 -> 372 | M84: 抖音叔叔 | N84: 26年1月
A85: 胜利女神 | B85: 良笑塑美 | C85: 红莲 | D85: 760 | E85: 0 | G85: 留存 | H85: =D85+E85+F85 -> 760 | M85: 拼多多 | N85: 26年1月
A86: 奥特曼 | B86: Alphamax | C86: 迪迦奥特曼 强力型 | D86: 582 | E86: 0 | G86: 留存 | H86: =D86+E86+F86 -> 582 | M86: 抖音模玩熊 | N86: 26年2月
A87: 数码宝贝 | B87: Mega House | C87: 钢铁加鲁鲁再版 | D87: 158 | E87: 786 | G87: 留存 | H87: =D87+E87+F87 -> 944 | M87: 猫受屋 | N87: 26年1月
A88: Ogre | B88: PINKMANGO | C88: 魅魔寄宿 咲舞紫织 圣诞服 | D88: 259 | E88: 894 | G88: 留存 | H88: =D88+E88+F88 -> 1153 | M88: 淘宝橘子屋 | N88: 26年2月，特別版
A89: 魔法少女小圆 | B89: F:NEX | C89: 鹿目圆 -盛装- | D89: 150 | E89: 685 | G89: 留存 | H89: =D89+E89+F89 -> 835 | M89: 叔叔会员购 | N89: 26年1月
A90: 爱与演唱会！阳光！！ | B90: Alter | C90: 国木田花丸 | D90: 131 | E90: 665 | G90: 留存 | H90: =D90+E90+F90 -> 796 | M90: 叔叔会员购 | N90: 26年3月
A91: 爱与演唱会！阳光！！ | B91: Alter | C91: 松浦果南 潜水服 | D91: 131 | E91: 633 | G91: 留存 | H91: =D91+E91+F91 -> 764 | M91: 叔叔会员购 | N91: 26年3月
A92: 无职转生 | B92: Mega House | C92: 洛琪希 | D92: 193 | E92: 939 | G92: 留存 | H92: =D92+E92+F92 -> 1132 | M92: kimi | N92: 26年3月
A93: チュロス | B93: Vibrastar | C93: 蜜姬 | D93: 235 | E93: 830 | G93: 留存 | H93: =D93+E93+F93 -> 1065 | M93: 淘宝橘子屋 | N93: 26年3月
B94: HopDo Toys | C94: 莫西干哥布林 | D94: 29 | E94: 129 | G94: 留存 | H94: =D94+E94+F94 -> 158 | M94: kimi | N94: 26年3月
A95: DISH | B95: quesQ | C95: 神官希卜娜 | D95: 180 | E95: 788 | G95: 留存 | H95: =D95+E95+F95 -> 968 | M95: kimi | N95: 26年5月
A96: YD | B96: Vibrastar | C96: 吸血鬼·米娜 | D96: 244 | E96: 1028 | G96: 留存 | H96: =D96+E96+F96 -> 1272 | M96: 淘宝橘子屋 | N96: 26年6月
A97: 星光咖啡馆与死神之蝶 | B97: Alice Glint | C97: 四季夏目 旗袍 | D97: 256 | E97: 1241 | G97: 留存 | H97: =D97+E97+F97 -> 1497 | M97: 淘宝橘子屋 | N97: 26年4月，卖
A98: DARLING in the FRANXX | B98: GSC | C98: 零二 | D98: 139 | E98: 681 | G98: 留存 | H98: =D98+E98+F98 -> 820 | M98: 猫受屋 | N98: 26年5月
A99: CW | B99: Vibrastar | C99: 紫音 -蓝蝶- | D99: 175 | E99: 850 | G99: 留存 | H99: =D99+E99+F99 -> 1025 | M99: 淘宝橘子屋 | N99: 26年6月
A100: 初音未来 | B100: GSC | C100: 流星时尚风格 | D100: 72 | H100: =D100+E100+F100 -> 72 | I100: 72 | J100: 0 | K100: =J100-I100 -> -72 | L100: =ROUND(K100/I100,4) -> -1 | M100: 指乐无穷 | N100: 26年6月，弃单
...

Sheet 抖音
A1: IP | B1: 系列名称 | C1: 名称 | D1: 买时状态 | E1: 状态 | F1: 总价 | G1: 卖出成本 | H1: 卖出价格 | I1: 利润 | J1: 利润率 | K1: 备注
A2: 龙珠 | B2: BWFC | C2: 蓝发悟吉塔01色 | D2: 全新 | E2: 留存 | F2: 115 | M2: 总花销 | N2: =SUM(F:F) -> 10862
A3: 龙珠 | B3: Gxmateria | C3: 龟仙人 | D3: 全新 | E3: 留存 | F3: 45 | M3: 总卖出 | N3: =SUM(H:H) -> 8461
A4: 龙珠 | B4: Gxmateria | C4: 巴达克 | D4: 全新 | E4: 卖出 | F4: 44 | G4: 44 | H4: 51 | I4: =H4-G4 -> 7 | J4: =I4/G4 -> 0.15909091 | M4: 总卖出成本 | N4: =SUM(G:G) -> 7626
A5: 龙珠 | B5: Gxmateria | C5: 踩波悟空 | D5: 全新 | E5: 卖出 | F5: 37 | G5: 37 | H5: 53 | I5: =H5-G5 -> 16 | J5: =I5/G5 -> 0.43243243 | M5: 利润 | N5: =SUM(I:I) -> 835
A6: 龙珠 | B6: HG | C6: 布欧全形态 | D6: 全新 | E6: 卖出 | F6: 399 | G6: 399 | H6: 415 | I6: =H6-G6 -> 16 | J6: =I6/G6 -> 0.040100251 | M6: 利润率 | N6: =ROUND(N5/N4,4) -> 0.1095
A7: 鬼灭之刃 | B7: WCF | C7: 主公大人面前 | D7: 全新 | E7: 留存 | F7: 147 | M7: 实际支出 | N7: =N2-N3 -> 2401
A8: 鬼灭之刃 | B8: WCF | C8: 炭治郎 | D8: 全新 | E8: 留存 | F8: 149
A9: 美少女战士 | B9: 闪耀魅力 | C9: 水兵月 | D9: 全新 | E9: 留存 | F9: 59 | K9: 已拆
A10: 奥特曼 | B10: SHF | C10: 特利伽奥特曼 | D10: 全新 | E10: 卖出 | F10: 124 | G10: 124 | H10: 139 | I10: =H10-G10 -> 15 | J10: =I10/G10 -> 0.12096774
A11: 奥特曼 | B11: SHF | C11: 特利伽奥特曼 | D11: 全新 | E11: 卖出 | F11: 130 | G11: 130 | H11: 143 | I11: =H11-G11 -> 13 | J11: =I11/G11 -> 0.1
A12: 奥特曼 | B12: SHF | C12: 特利伽奥特曼 | D12: 全新 | E12: 卖出 | F12: 130 | G12: 130 | H12: 157 | I12: =H12-G12 -> 27 | J12: =I12/G12 -> 0.20769231
A13: 奥特曼 | B13: SHF | C13: 特利伽奥特曼 | D13: 全新 | E13: 卖出 | F13: 130 | G13: 130 | H13: 170 | I13: =H13-G13 -> 40 | J13: =I13/G13 -> 0.30769231
A14: 奥特曼 | B14: SHF | C14: 特利伽奥特曼 | D14: 全新 | E14: 卖出 | F14: 130 | G14: 130 | H14: 169 | I14: =H14-G14 -> 39 | J14: =I14/G14 -> 0.3
A15: 奥特曼 | B15: SHF | C15: 特利伽奥特曼 | D15: 全新 | E15: 卖出 | F15: 130 | G15: 130 | H15: 179 | I15: =H15-G15 -> 49 | J15: =I15/G15 -> 0.37692308
A16: 怪物猎人 | B16: SHM | C16: 雄火龙 | D16: 全新 | E16: 卖出 | F16: 500 | G16: 500 | H16: 557 | I16: =H16-G16 -> 57 | J16: =I16/G16 -> 0.114
A17: 火影忍者 | B17: SHF | C17: 鸣人 | D17: 全新 | E17: 卖出 | F17: 110 | G17: 110 | H17: 128 | I17: =H17-G17 -> 18 | J17: =I17/G17 -> 0.16363636
A18: 胜利女神：新的希望 | B18: S.K.P | C18: 桃乐丝 | D18: 全新 | E18: 卖出 | F18: 238 | G18: 238 | H18: 417 | I18: =H18-G18 -> 179 | J18: =I18/G18 -> 0.75210084
A19: 星光咖啡馆与死神之蝶 | B19: Alice Glint | C19: 四季夏目 旗袍 | D19: 全新 | E19: 卖出 | F19: 1396 | G19: 1396 | H19: 1460 | I19: =H19-G19 -> 64 | J19: =I19/G19 -> 0.045845272
A20: 星光咖啡馆与死神之蝶 | B20: Alice Glint | C20: 四季夏目 旗袍 | D20: 全新 | E20: 卖出 | F20: 1396 | G20: 1396 | H20: 1441 | I20: =H20-G20 -> 45 | J20: =I20/G20 -> 0.032234957
A21: 星光咖啡馆与死神之蝶 | B21: Alice Glint | C21: 四季夏目 旗袍 | D21: 全新 | E21: 卖出 | F21: 1400 | G21: 1400 | H21: 1471 | I21: =H21-G21 -> 71 | J21: =I21/G21 -> 0.050714286 | K21: 老于抖音
A22: 星光咖啡馆与死神之蝶 | B22: Alice Glint | C22: 四季夏目 旗袍 | D22: 全新 | E22: 卖出 | F22: 1332 | G22: 1332 | H22: 1511 | I22: =H22-G22 -> 179 | J22: =I22/G22 -> 0.13438438
A23: 星光咖啡馆与死神之蝶 | B23: Alice Glint | C23: 四季夏目 旗袍 | D23: 全新 | E23: 留存 | F23: 1427
A24: 星光咖啡馆与死神之蝶 | B24: Alice Glint | C24: 四季夏目 旗袍 | D24: 全新 | E24: 留存 | F24: 1294

Sheet 套书+单行本
A1: IP | B1: 种类 | C1: 出版社 | D1: 版本 | E1: 册数 | F1: 尺寸 | G1: 完结度 | H1: 作者 | I1: 买时状态 | J1: 首刷 | K1: 盒装 | L1: 状态 | M1: 总价 | N1: 返利 | O1: 实际价格 | P1: 卖出成本 | Q1: 卖出价格 | R1: 利润 | S1: 利润率 | T1: 渠道
A2: 龙珠 | B2: 漫画 | C2: 东立 | D2: 完全版 | E2: 34 | F2: 25K | G2: 完结 | H2: 鸟山明 | I2: 全新 | L2: 留存 | M2: 1939 | T2: 淘宝 | V2: 总花销 | W2: =SUM(M:M) -> 55327
A3: 龙珠 | B3: 漫画 | C3: 集英社 | D3: 40周年日版 | E3: 42 | F3: 36K | G3: 完结 | H3: 鸟山明 | I3: 全新 | L3: 留存 | M3: 1001 | T3: 京东 | V3: 总卖出 | W3: =SUM(Q:Q) -> 726
A4: 阿拉蕾 | B4: 漫画 | C4: 东立 | D4: 完全版 | E4: 15 | F4: 25K | G4: 完结 | H4: 鸟山明 | I4: 全新 | L4: 留存 | M4: 895 | T4: 京东 | V4: 总卖出成本 | W4: =SUM(P:P) -> 721
A5: 沙漠大冒险 | B5: 漫画 | C5: 四川美术 | D5: 简中 | E5: 1 | F5: 32K | G5: 完结 | H5: 鸟山明 | I5: 全新 | L5: 留存 | M5: 3 | T5: 京东 | V5: 利润 | W5: =SUM(R:R) -> 5
A6: 银河巡警加克 | B6: 漫画 | C6: 东立 | D6: 台版 | E6: 1 | F6: 36K | G6: 完结 | H6: 鸟山明 | I6: 全新 | L6: 留存 | M6: 12 | T6: 抖音 | V6: 利润率 | W6: =ROUND(W5/W4,4) -> 0.0069
A7: 桂＆明 桂正和✕鸟山明共同短篇集 | B7: 漫画 | C7: 东立 | D7: 台版 | E7: 1 | F7: 32K | G7: 完结 | H7: 鸟山明 | I7: 全新 | L7: 留存 | M7: 0 | T7: 抖音 | V7: 实际支出 | W7: =W2-W3 -> 54601
A8: 亚人 | B8: 漫画 | C8: 东立 | D8: 台版 | E8: 17 | F8: 32K | G8: 完结 | H8: 樱井画门 | I8: 全新 | L8: 留存 | M8: 520 | T8: 抖音
A9: 行星POOL | B9: 漫画 | C9: 东立 | D9: 台版 | E9: 1 | F9: 32K | G9: 完结 | H9: 樱井画门 | I9: 全新 | J9: 首限 | L9: 留存 | M9: 32 | T9: 抖音
A10: 异兽魔都 | B10: 漫画 | C10: 长鸿 | D10: 典藏版 | E10: 23 | F10: 32K | G10: 完结 | H10: 林田球 | I10: 全新 | L10: 留存 | M10: 1058 | T10: 博客来
A11: 鬼灭之刃 | B11: 漫画 | C11: 东立 | D11: 台版 | E11: 23 | F11: 36K | G11: 完结 | H11: 吾峠呼世晴 | I11: 全新 | L11: 留存 | M11: 404 | T11: 京东
A12: 幽游白书 | B12: 漫画 | C12: 中信 | D12: 简中 | F12: 25K | G12: 完结 | H12: 富㭴义博 | I12: 全新 | L12: 留存 | M12: 131 | T12: 拼多多，出
A13: 幽游白书 | B13: 漫画 | C13: 东立 | D13: 完全版 | E13: 15 | F13: 25K | G13: 完结 | H13: 富㭴义博 | I13: 全新 | L13: 留存 | M13: 664 | T13: 京东
A14: 伊藤润二 | B14: 漫画 | C14: 东立 | D14: 爱藏版 | E14: 11 | F14: 32K | G14: 完结 | H14: 伊藤润二 | I14: 全新 | L14: 留存 | M14: 639 | T14: 博客来
A15: 伊藤润二 4 至死不渝的爱 | B15: 漫画 | C15: 东立 | D15: 爱藏版 | E15: 1 | F15: 32K | G15: 完结 | H15: 伊藤润二 | I15: 拆摆 | L15: 留存 | M15: 20 | T15: 抖音
A16: 旋涡 | B16: 漫画 | C16: 小学馆 | D16: 日版 | E16: 1 | F16: 32K | G16: 完结 | H16: 伊藤润二 | I16: 全新 | L16: 留存 | M16: 65 | T16: 日本带回
A17: 伊藤润二展 诱惑 Illustrations | B17: 画集 | C17: 朝日新闻 | D17: 日版 | E17: 1 | F17: 16K | G17: 完结 | H17: 伊藤润二 | I17: 全新 | L17: 留存 | M17: 176 | T17: 日本带回
A18: 伊藤润二展 诱惑 Illustrations | B18: 画集 | C18: 东立 | D18: 台版 | E18: 1 | F18: 16K | G18: 完结 | H18: 伊藤润二 | I18: 全新 | L18: 留存 | M18: 134 | T18: 抖音
A19: 禁入空间 | B19: 漫画 | C19: 东立 | D19: 台版 | E19: 1 | F19: 25K | G19: 完结 | H19: 伊藤润二 | I19: 全新 | L19: 留存 | M19: 69 | T19: 抖音
A20: 幻怪地带 | B20: 漫画 | C20: 东立 | D20: 台版 | E20: 1 | F20: 25K | G20: 完结 | H20: 伊藤润二 | I20: 全新 | L20: 留存 | M20: 55 | T20: 抖音
A21: 幻怪地带 以太村 | B21: 漫画 | C21: 东立 | D21: 台版 | E21: 1 | F21: 25K | G21: 完结 | H21: 伊藤润二 | I21: 全新 | L21: 留存 | M21: 55 | T21: 抖音
A22: 感应 | B22: 漫画 | C22: 东立 | D22: 台版 | E22: 1 | F22: 32K | G22: 完结 | H22: 伊藤润二 | I22: 全新 | L22: 留存 | M22: 46 | T22: 抖音
A23: 地狱星 | B23: 漫画 | C23: 东立 | D23: 台版 | E23: 1 | F23: 32K | G23: 完结 | H23: 伊藤润二 | I23: 全新 | L23: 留存 | M23: 41 | T23: 抖音
A24: 黑色诡局 | B24: 漫画 | C24: 东立 | D24: 台版 | E24: 1 | F24: 36K | G24: 完结 | H24: 伊藤润二 | I24: 全新 | L24: 留存 | M24: 41 | T24: 抖音
... A38: 守护甜心 5 | B38: 漫画 | C38: 长鸿 | D38: 爱藏版 | E38: 1 | F38: 25K | G38: 完结 | H38: 江原涉子 | I38: 全新 | L38: 留存 | M38: 32 | T38: 抖音
A39: 守护甜心 6 | B39: 漫画 | C39: 长鸿 | D39: 爱藏版 | E39: 1 | F39: 25K | G39: 完结 | H39: 江原涉子 | I39: 全新 | L39: 留存 | T39: 抖音
A40: 浪客行 | B40: 漫画 | C40: 尖端 | D40: 台版 | E40: 37 | F40: 32K | G40: 完结 | H40: 井上雄彦 | I40: 全新 | L40: 留存 | M40: 963 | T40: 京东
A41: SLAM DUNK 灌篮高手总集篇 | B41: 漫画 | C41: 尖端 | D41: 台版 | E41: 1 | F41: 16K | G41: 完结 | H41: 井上雄彦 | I41: 全新 | L41: 留存 | M41: 25 | T41: 抖音
A42: 纯真之人 | B42: 漫画 | C42: 尖端 | D42: 台版 | E42: 9 | F42: 32K | G42: 完结 | H42: 坂本真一 | I42: 全新 | L42: 留存 | M42: 265 | T42: 抖音
A43: 灵能百分百+番外 | B43: 漫画 | C43: 湖南文艺 | D43: 简中 | E43: 17 | F43: 32K | G43: 完结 | H43: ONE | I43: 全新 | L43: 留存 | M43: 126 | T43: 淘宝
A44: 电锯人 最佳拍档 | B44: 轻小说 | E44: 1 | F44: 32K | G44: 完结 | H44: 藤本树 | I44: 全新 | L44: 留存 | M44: 17 | T44: 淘宝
A45: 蓦然回首 再见绘梨 | B45: 漫画 | E45: 2 | F45: 32K | G45: 完结 | H45: 藤本树 | I45: 全新 | L45: 留存 | M45: 18 | T45: 淘宝
A46: 炎拳 | B46: 漫画 | C46: 东立 | D46: 台版 | E46: 8 | F46: 36K | G46: 完结 | H46: 藤本树 | I46: 全新 | L46: 留存 | M46: 130 | T46: 淘宝
A47: 17-21 22-26 | B47: 漫画 | E47: 2 | F47: 32K | G47: 完结 | H47: 藤本树 | I47: 全新 | L47: 留存 | M47: 22 | T47: 淘宝
A48: 美少女战士 | B48: 漫画 | C48: 青文 | D48: 完全版 | E48: 10 | F48: 25K | G48: 完结 | H48: 武内直子 | I48: 全新 | L48: 留存 | M48: 713 | T48: 京东
A49: 关于地球的运动 1-4 | B49: 漫画 | C49: 九州 | D49: 简中 | E49: 4 | F49: 32K | G49: 完结 | H49: 鱼丰 | I49: 全新 | L49: 留存 | M49: 48 | T49: 京东
A50: 关于地球的运动 5-8 | B50: 漫画 | C50: 九州 | D50: 简中 | E50: 4 | F50: 32K | G50: 完结 | H50: 鱼丰 | I50: 全新 | L50: 留存 | M50: 31 | T50: 京东
A51: 夏日重现 | B51: 漫画 | C51: 东立 | D51: 台版 | E51: 13 | F51: 36K | G51: 完结 | H51: 田中靖规 | I51: 全新 | L51: 留存 | M51: 264 | T51: 小红书 胖猪号
A52: H2 | B52: 漫画 | C52: 青文 | D52: 典藏版 | E52: 17 | F52: 32K | G52: 完结 | H52: 安达充 | I52: 全新 | L52: 留存 | M52: 583 | T52: 小红书 杨树林
A53: 青春方程式 | B53: 漫画 | C53: 新星 | D53: 简中 | E53: 3 | F53: 32K | G53: 完结 | H53: 安达充 | I53: 全新 | L53: 留存 | M53: 34 | T53: 京东
A54: 彩虹辣椒 | B54: 漫画 | C54: 青文 | D54: 典藏版 | E54: 5 | F54: 25K | G54: 完结 | H54: 安达充 | I54: 全新 | K54: 盒装 | L54: 留存 | M54: 311 | T54: 京东
A55: KATSU! | B55: 漫画 | C55: 青文 | D55: 典藏版 | E55: 8 | F55: 25K | G55: 完结 | H55: 安达充 | I55: 全新 | K55: 盒装 | L55: 留存 | M55: 388 | T55: 抖音
A56: ROUGH | B56: 漫画 | C56: 青文 | D56: 典藏版 | E56: 6 | F56: 25K | G56: 完结 | H56: 安达充 | I56: 全新 | K56: 盒装 | L56: 留存 | M56: 158 | T56: 淘宝
A57: 四叶游戏 | B57: 漫画 | C57: 青文 | D57: 典藏版 | E57: 9 | F57: 32K | G57: 完结 | H57: 安达充 | I57: 全新 | K57: 盒装 | L57: 留存 | M57: 436 | T57: 淘宝
A58: 火鸟 | B58: 漫画 | C58: 东贩 | D58: 台版 | E58: 12 | F58: 32K | G58: 完结 | H58: 手冢治虫 | I58: 全新 | L58: 留存 | M58: 574 | T58: 京东
A59: 漫画大学 | B59: 漫画 | C59: 东立 | D59: 台版 | E59: 1 | F59: 25K | G59: 完结 | H59: 手冢治虫 | I59: 全新 | L59: 留存 | M59: 15 | T59: 抖音
A60: 漫画生物学 | B60: 漫画 | C60: 东立 | D60: 台版 | E60: 1 | F60: 25K | G60: 完结 | H60: 手冢治虫 | I60: 全新 | L60: 留存 | M60: 15 | T60: 抖音
A61: 伪恋 1-13 | B61: 漫画 | C61: 东立 | D61: 爱藏版 | E61: 13 | F61: 32K | G61: 连载中 | H61: 古味直志 | I61: 全新 | L61: 留存 | M61: 568
A62: 伪恋 1-5 | B62: 漫画 | C62: 东立 | D62: 爱藏版 | E62: 5 | F62: 32K | G62: 连载中 | H62: 古味直志 | I62: 全新 | L62: 留存 | T62: 京东 206
A63: 伪恋 6 | B63: 漫画 | C63: 东立 | D63: 爱藏版 | E63: 1 | F63: 32K | G63: 连载中 | H63: 古味直志 | I63: 全新 | L63: 留存 | T63: 京东 42
A64: 伪恋 7 | B64: 漫画 | C64: 东立 | D64: 爱藏版 | E64: 1 | F64: 32K | G64: 连载中 | H64: 古味直志 | I64: 全新 | L64: 留存 | T64: 淘宝 45
A65: 伪恋 8 | B65: 漫画 | C65: 东立 | D65: 爱藏版 | E65: 1 | F65: 32K | G65: 连载中 | H65: 古味直志 | I65: 全新 | L65: 留存 | T65: 京东 43
A66: 伪恋 9 | B66: 漫画 | C66: 东立 | D66: 爱藏版 | E66: 1 | F66: 32K | G66: 连载中 | H66: 古味直志 | I66: 全新 | L66: 留存 | T66: 京东 43
A67: 伪恋 10 | B67: 漫画 | C67: 东立 | D67: 爱藏版 | E67: 1 | F67: 32K | G67: 连载中 | H67: 古味直志 | I67: 全新 | L67: 留存 | T67: 淘宝 46
A68: 伪恋 11 | B68: 漫画 | C68: 东立 | D68: 爱藏版 | E68: 1 | F68: 32K | G68: 连载中 | H68: 古味直志 | I68: 全新 | L68: 留存 | T68: 淘宝 48
A69: 伪恋 12 | B69: 漫画 | C69: 东立 | D69: 爱藏版 | E69: 1 | F69: 32K | G69: 连载中 | H69: 古味直志 | I69: 全新 | L69: 留存 | T69: 淘宝 47
A70: 伪恋 13 | B70: 漫画 | C70: 东立 | D70: 爱藏版 | E70: 1 | F70: 32K | G70: 连载中 | H70: 古味直志 | I70: 全新 | L70: 留存 | T70: 抖音 48
A71: 伪恋 14 | B71: 漫画 | C71: 东立 | D71: 爱藏版 | E71: 1 | F71: 32K | G71: 连载中 | H71: 古味直志 | I71: 全新 | L71: 留存 | M71: 128 | T71: 闲鱼
A72: 少女终末旅行 | B72: 漫画 | C72: 天津人民美术 | D72: 简中 | E72: 6 | F72: 32K | G72: 完结 | H72: つくみず | I72: 全新 | L72: 留存 | M72: 61 | T72: 京东
A73: 爆漫王 | B73: 漫画 | C73: 安徽少年儿童 | D73: 简中 | E73: 20 | F73: 36K | G73: 完结 | H73: 小畑健 | I73: 全新 | L73: 留存 | M73: 95 | T73: 京东
A74: 明日边缘 | B74: 漫画 | C74: 四川科学技术 | D74: 简中 | E74: 2 | F74: 32K | G74: 完结 | H74: 小畑健 | I74: 全新 | L74: 留存 | M74: 6 | T74: 京东
A75: 电影少女 | B75: 漫画 | C75: 东立 | D75: 台版 | E75: 9 | F75: 32K | G75: 完结 | H75: 桂正和 | I75: 全新 | L75: 留存 | M75: 680 | T75: 闲鱼
A76: 电影少女 | B76: 漫画 | C76: 东立 | D76: 台版 | E76: 9 | F76: 32K | G76: 完结 | H76: 桂正和 | I76: 全新 | L76: 留存 | M76: 564 | T76: 抖音，卖
A77: IS | B77: 漫画 | C77: 东立 | D77: 完全版 | E77: 12 | F77: 25K | G77: 完结 | H77: 桂正和 | I77: 全新 | L77: 留存 | M77: 1007 | T77: 抖音
A78: IS | B78: 漫画 | C78: 东立 | D78: 完全版 | E78: 12 | F78: 25K | G78: 完结 | H78: 桂正和 | I78: 全新 | L78: 留存 | M78: 737 | N78: 72 | O78: 666 | T78: 京东，卖
A79: 搞怪家庭 | B79: 漫画 | C79: 尖端 | D79: 珍藏版 | E79: 11 | F79: 32K | G79: 完结 | H79: 北条司 | I79: 全新 | L79: 留存 | M79: 1005 | T79: 博客来 盒装
A80: 钢之炼金术师1-9（银盒） | B80: 漫画 | C80: 尖端 | D80: 台版 | E80: 9 | F80: 25K | G80: 完结 | H80: 荒川弘 | I80: 全新 | K80: 盒装 | L80: 留存 | M80: 411 | T80: 淘宝
A81: 钢之炼金术师10-18（黑盒） | B81: 漫画 | C81: 尖端 | D81: 台版 | E81: 9 | F81: 25K | G81: 完结 | H81: 荒川弘 | I81: 全新 | K81: 盒装 | L81: 留存 | M81: 280 | T81: 抖音 微瑕
A82: 钢之炼金术师10-18（银盒） | B82: 漫画 | C82: 尖端 | D82: 台版 | E82: 9 | F82: 25K | G82: 完结 | H82: 荒川弘 | I82: 全新 | K82: 盒装 | L82: 留存 | M82: 453 | T82: 淘宝
A83: 怪物 | B83: 漫画 | C83: 东立 | D83: 完全版 | E83: 9 | F83: 25K | G83: 完结 | H83: 浦泽直树 | I83: 全新 | L83: 留存 | M83: 553 | T83: 京东
A84: NASA太空梦 | B84: 漫画 | C84: 东立 | D84: 台版 | E84: 1 | F84: 32K | G84: 完结 | H84: 浦泽直树 | I84: 全新 | K84: 盒装 | L84: 留存 | M84: 51 | T84: 抖音
A85: 大蛇 | B85: 漫画 | C85: 尖端 | D85: 台版 | E85: 4 | F85: 32K | G85: 完结 | H85: 楳图一雄 | I85: 全新 | L85: 留存 | M85: 253 | T85: 京东
A86: 漂流教室 | B86: 漫画 | C86: 尖端 | D86: 台版 | E86: 6 | F86: 32K | G86: 完结 | H86: 楳图一雄 | I86: 全新 | L86: 留存 | M86: 295 | T86: 京东
A87: 洗礼 | B87: 漫画 | C87: 尖端 | D87: 完全版 | E87: 3 | F87: 32K | G87: 完结 | H87: 楳图一雄 | I87: 全新 | L87: 留存 | M87: 255 | T87: 抖音
A88: 14岁 | B88: 漫画 | C88: 尖端 | D88: 完全版 | E88: 13 | F88: 25K | G88: 完结 | H88: 楳图一雄 | I88: 全新 | K88: 盒装 | L88: 留存 | M88: 845 | T88: 微店
A89: 我是真悟 | B89: 漫画 | C89: 尖端 | D89: 完全版 | E89: 6 | F89: 25K | G89: 完结 | H89: 楳图一雄 | I89: 全新 | K89: 盒装 | L89: 留存 | M89: 670 | T89: 星愿书店（运费170）卖
A90: 我是真悟 | B90: 漫画 | C90: 尖端 | D90: 完全版 | E90: 6 | F90: 25K | G90: 完结 | H90: 楳图一雄 | I90: 全新 | K90: 盒装 | L90: 留存 | M90: 670 | T90: 星愿书店（运费168）
A91: 我的学生会长是女仆 | B91: 漫画 | C91: 长鸿 | D91: 台版 | E91: 18 | F91: 36K | G91: 完结 | H91: 藤原飞吕 | I91: 全新 | L91: 留存 | M91: 260 | T91: 京东
A92: 新世纪福音战士 | B92: 漫画 | C92: 角川 | D92: 完全版 | E92: 7 | F92: 25K | G92: 完结 | H92: 贞本义行 | I92: 全新 | L92: 留存 | M92: 355 | T92: 京东
A93: 相聚一刻 | B93: 漫画 | C93: 尖端 | D93: 典藏版 | E93: 10 | F93: 25K | G93: 完结 | H93: 高桥留美子 | I93: 全新 | L93: 留存 | M93: 422 | T93: 京东 王哥号
A94: 金田一少年事件簿R | B94: 漫画 | C94: 东立 | D94: 台版 | E94: 14 | F94: 36K | G94: 完结 | H94: 天树征丸 | I94: 全新 | L94: 留存 | M94: 270 | T94: 淘宝
A95: 金田一20周年 | B95: 漫画 | C95: 东立 | D95: 台版 | E95: 5 | F95: 36K | G95: 完结 | H95: 天树征丸 | I95: 全新 | L95: 留存 | M95: 97 | T95: 淘宝
A96: 恶之华 | B96: 漫画 | C96: 东立 | D96: 台版 | E96: 11 | F96: 32K | G96: 完结 | H96: 押见修造 | I96: 全新 | L96: 留存 | M96: 280 | T96: 京东
A97: 漂流网咖 | B97: 漫画 | C97: 东立 | D97: 台版 | E97: 7 | F97: 32K | G97: 完结 | H97: 押见修造 | I97: 全新 | L97: 留存 | M97: 350 | T97: 闲鱼
A98: 小千 | B98: 漫画 | C98: 东立 | D98: 台版 | E98: 1 | F98: 32K | G98: 完结 | H98: 押见修造 | I98: 全新 | L98: 留存 | M98: 38 | T98: 抖音
A99: 斩赤红之瞳 | B99: 漫画 | C99: 青文 | D99: 台版 | E99: 15 | F99: 32K | G99: 完结 | H99: タカヒロ | I99: 全新 | L99: 留存 | M99: 515 | T99: 微店，6和14微瑕
A100: 斩赤红之瞳 零 | B100: 漫画 | C100: 青文 | D100: 台版 | E100: 10 | F100: 32K | G100: 完结 | H100: タカヒロ | I100: 全新 | L100: 留存 | M100: 352 | T100: 抖音
A101: ORIGIN-源型机 | B101: 漫画 | C101: 东贩 | D101: 台版 | E101: 10 | F101: 32K | G101: 完结 | H101: Boichi | I101: 全新 | L101: 留存 | M101: 299 | T101: 抖音 小号
A102: 厄夜怪客 | B102: 漫画 | C102: 东立 | D102: 爱藏版 | E102: 5 | F102: 32K | G102: 完结 | H102: 平野耕太 | I102: 全新 | K102: 盒装 | L102: 留存 | M102: 309 | T102: 微店
A103: 葬送的芙莉莲 同人合集～徜徉另一趟旅程的魔法～ | B103: 漫画 | C103: 东立 | D103: 台版 | E103: 1 | F103: 32K | G103: 完结 | H103: 山田钟人 | I103: 全新 | L103: 留存 | M103: 13 | T103: 抖音
A104: 葬送的芙莉莲 | B104: 公式书 | C104: 东立 | D104: 台版 | E104: 1 | F104: 32K | G104: 连载中 | H104: 山田钟人 | I104: 全新 | L104: 留存 | M104: 16 | T104: 抖音
A105: 无实之花 | B105: 漫画 | C105: 东立 | D105: 台版 | E105: 3 | F105: 32K | G105: 完结 | H105: NON | I105: 全新 | L105: 留存 | M105: 190 | T105: 闲鱼
A106: 偷窥孔 | B106: 漫画 | C106: 东立 | D106: 台版 | E106: 13 | F106: 32K | G106: 完结 | H106: 本名和幸 | I106: 全新 | L106: 留存 | M106: 563 | T106: 闲鱼，运费143，限
A107: 出包王女 第一部(10)+第二部(9) | B107: 漫画 | C107: 东立 | D107: 台版 | E107: 19 | F107: 32K | G107: 完结 | H107: 矢吹健太朗 | I107: 全新 | L107: 留存 | M107: 1850 | T107: 闲鱼，限
A108: 妖幻三重奏 | B108: 漫画 | C108: 东立 | D108: 台版 | E108: 16 | F108: 32K | G108: 完结 | H108: 矢吹健太朗 | I108: 全新 | J108: 14-16 | L108: 留存 | M108: 769 | T108: 闲鱼，限 1-3拆
A109: 晚安布布 | B109: 漫画 | C109: 东贩 | D109: 台版 | E109: 13 | F109: 32K | G109: 完结 | H109: 浅野一二〇 | I109: 全新 | L109: 留存 | M109: 520 | T109: 闲鱼，7和13有瑕
A110: 恶魔的破坏 | B110: 漫画 | C110: 东贩 | D110: 台版 | E110: 12 | F110: 32K | G110: 完结 | H110: 浅野一二〇 | I110: 全新 | L110: 留存 | M110: 204 | T110: 淘宝
A111: 多美好的人生 | B111: 漫画 | C111: 玉皇朝 | D111: 港版 | E111: 1 | F111: 25K | G111: 完结 | H111: 浅野一二〇 | I111: 全新 | L111: 留存 | M111: 79 | T111: 抖音
A112: 天降之物 | B112: 漫画 | C112: 角川 | D112: 台版 | E112: 20 | F112: 32K | G112: 完结 | H112: 水无月嵩 | I112: 全新 | L112: 卖出 | M112: 721 | P112: 721 | Q112: 726 | R112: =Q112-P112 -> 5 | S112: =R112/P112 -> 0.0069348128 | T112: 博客来 拆一本
A113: 天降之物 | B113: 漫画 | C113: 角川 | D113: 台版 | E113: 20 | F113: 32K | G113: 完结 | H113: 水无月嵩 | I113: 全新 | L113: 留存 | M113: 745 | T113: 抖音
...

Sheet 散本+未完结
A1: IP | B1: 种类 | C1: 出版社 | D1: 版本 | E1: 册数 | F1: 尺寸 | G1: 完结度 | H1: 作者 | I1: 买时状态 | J1: 首刷 | K1: 盒装 | L1: 状态 | M1: 总价 | N1: 卖出成本 | O1: 卖出价格 | P1: 利润 | Q1: 利润率 | R1: 渠道
A2: 龙珠 超全集 1 | B2: 公式书 | C2: 香港文化传信 | D2: 港版 | E2: 1 | F2: 16K | G2: 完结 | H2: 鸟山明 | I2: 全新 | L2: 留存 | M2: 158 | R2: 抖音 卖 | T2: 总花销 | U2: =SUM(M:M) -> 20435
A3: 龙珠 超全集 1 | B3: 公式书 | C3: 香港文化传信 | D3: 港版 | E3: 1 | F3: 16K | G3: 完结 | H3: 鸟山明 | I3: 全新 | L3: 留存 | M3: 135 | R3: 抖音 | T3: 总卖出 | U3: =SUM(O:O) -> 0
A4: 龙珠 超全集 2 | B4: 公式书 | C4: 香港文化传信 | D4: 港版 | E4: 1 | F4: 16K | G4: 完结 | H4: 鸟山明 | I4: 全新 | L4: 留存 | M4: 158 | R4: 抖音 | T4: 总卖出成本 | U4: =SUM(N:N) -> 0
A5: 龙珠 超全集 3 | B5: 公式书 | C5: 香港文化传信 | D5: 港版 | E5: 1 | F5: 16K | G5: 完结 | H5: 鸟山明 | I5: 全新 | L5: 留存 | R5: 抖音 | T5: 利润 | U5: =SUM(P:P) -> 0
A6: 龙珠 超全集 4 | B6: 公式书 | C6: 香港文化传信 | D6: 港版 | E6: 1 | F6: 16K | G6: 完结 | H6: 鸟山明 | I6: 全新 | L6: 留存 | T6: 利润率 | U6: =ROUND(U5/U4,4) -> #DIV/0!
A7: 大黑暗 1-7 | B7: 漫画 | C7: 东立 | D7: 台版 | E7: 7 | F7: 32K | G7: 连载中 | H7: 林田球 | I7: 全新 | L7: 留存 | M7: 331 | R7: 淘宝 | T7: 实际支出 | U7: =U2-U3 -> 20435
A8: 大黑暗 8 | B8: 漫画 | C8: 东立 | D8: 台版 | E8: 1 | F8: 32K | G8: 连载中 | H8: 林田球 | I8: 全新 | L8: 留存 | R8: 小红书
A9: 败犬女主 1-7+SSS | B9: 轻小说 | C9: 东立 | D9: 台版 | E9: 8 | F9: 32K | G9: 连载中 | H9: 雨森焚火 | I9: 全新 | L9: 留存 | M9: 278 | R9: 京东
A10: 败犬女主 8 | B10: 轻小说 | C10: 东立 | D10: 台版 | E10: 1 | F10: 32K | G10: 连载中 | H10: 雨森焚火 | I10: 全新 | L10: 留存 | M10: 29 | R10: 京东
A11: 败犬女主 8.5 | B11: 轻小说 | C11: 东立 | D11: 台版 | E11: 1 | F11: 32K | G11: 连载中 | H11: 雨森焚火 | I11: 全新 | J11: 首限 | L11: 留存 | M11: 99 | R11: 抖音
A12: 全职猎人 | B12: 漫画 | C12: 东立 | D12: 台版 | E12: 38 | F12: 36K | G12: 连载中 | H12: 富㭴义博 | I12: 全新 | L12: 留存 | M12: 535 | R12: 淘宝
A13: 孤高之人 1-12 | B13: 漫画 | C13: 尖端 | D13: 台版 | E13: 12 | F13: 32K | G13: 连载中 | H13: 坂本真一 | I13: 全新 | L13: 留存 | M13: 254 | R13: 京东
A14: 孤高之人 13 | B14: 漫画 | C14: 尖端 | D14: 台版 | E14: 1 | F14: 32K | G14: 连载中 | H14: 坂本真一 | I14: 全新 | L14: 留存 | M14: 20 | R14: 抖音
A15: 孤高之人 14 | B15: 漫画 | C15: 尖端 | D15: 台版 | E15: 1 | F15: 32K | G15: 连载中 | H15: 坂本真一 | I15: 全新 | L15: 留存 | M15: 21 | R15: 博客来
A16: 孤高之人 15 | B16: 漫画 | C16: 尖端 | D16: 台版 | E16: 1 | F16: 32K | G16: 连载中 | H16: 坂本真一 | I16: 全新 | L16: 留存
A17: 孤高之人 16 | B17: 漫画 | C17: 尖端 | D17: 台版 | E17: 1 | F17: 32K | G17: 连载中 | H17: 坂本真一 | I17: 全新 | L17: 留存
A18: 孤高之人 17 | B18: 漫画 | C18: 尖端 | D18: 台版 | E18: 1 | F18: 32K | G18: 连载中 | H18: 坂本真一 | I18: 全新 | L18: 留存
A19: 纯真之人 Rough 1-6 | B19: 漫画 | C19: 尖端 | D19: 台版 | E19: 6 | F19: 32K | G19: 连载中 | H19: 坂本真一 | I19: 全新 | L19: 留存 | M19: 211 | R19: 抖音
A20: 隐藏技能 BUG EGO 1 | B20: 漫画 | C20: 东立 | D20: 台版 | E20: 1 | F20: 32K | G20: 连载中 | H20: ONE | I20: 全新 | L20: 留存 | M20: 19 | R20: 抖音
A21: 隐藏技能 BUG EGO 2 | B21: 漫画 | C21: 东立 | D21: 台版 | E21: 1 | F21: 32K | G21: 连载中 | H21: ONE | I21: 全新 | L21: 留存 | M21: 14 | R21: 抖音
A22: 隐藏技能 BUG EGO 3 | B22: 漫画 | C22: 东立 | D22: 台版 | E22: 1 | F22: 32K | G22: 连载中 | H22: ONE | I22: 全新 | J22: 首限 | L22: 留存 | M22: 35 | R22: 抖音
A23: 伪恋 14 | B23: 漫画 | C23: 东立 | D23: 爱藏版 | E23: 1 | F23: 32K | G23: 连载中 | H23: 古味直志 | I23: 全新 | L23: 留存 | R23: 会员购
A24: 天使心1st 1-8 | B24: 漫画 | C24: 尖端 | D24: 典藏版 | E24: 8 | F24: 25K | G24: 完结 | H24: 北条司 | I24: 全新 | K24: 盒装 | L24: 留存 | M24: 202 | R24: 淘宝 瑕疵版
A25: 天使心1st 9-16 | B25: 漫画 | C25: 尖端 | D25: 典藏版 | E25: 8 | F25: 25K | G25: 完结 | H25: 北条司 | I25: 全新 | K25: 盒装 | L25: 留存 | M25: 445 | R25: 抖音
A26: 天使心1st 17-24 | B26: 漫画 | C26: 尖端 | D26: 典藏版 | E26: 8 | F26: 25K | G26: 完结 | H26: 北条司 | I26: 全新 | K26: 盒装 | L26: 留存 | M26: 416 | R26: 京东
A27: 天使心2nd 1-8 | B27: 漫画 | C27: 尖端 | D27: 典藏版 | E27: 8 | F27: 25K | G27: 完结 | H27: 北条司 | I27: 全新 | K27: 盒装 | L27: 留存 | M27: 319 | R27: 淘宝
A28: 天使心2nd 9-16 | B28: 漫画 | C28: 尖端 | D28: 典藏版 | E28: 8 | F28: 25K | G28: 完结 | H28: 北条司 | I28: 全新 | K28: 盒装 | L28: 留存 | M28: 365 | R28: 京东
A29: 城市猎人17-24 | B29: 漫画 | C29: 尖端 | D29: 完全版 | E29: 8 | F29: 25K | G29: 完结 | H29: 北条司 | I29: 拆摆 | L29: 留存 | M29: 350 | R29: 抖音 瑕疵版
A30: 城市猎人25-32 | B30: 漫画 | C30: 尖端 | D30: 完全版 | E30: 8 | F30: 25K | G30: 完结 | H30: 北条司 | I30: 拆摆 | L30: 留存 | M30: 297 | R30: 抖音 瑕疵版
A31: 北条司短篇集（三本） | B31: 漫画 | C31: 玉皇朝 | D31: 珍藏版 | E31: 3 | F31: 32K | G31: 完结 | H31: 北条司 | I31: 全新 | L31: 留存 | M31: 167 | R31: 抖音 《艳阳少女》，《RASH!! 辣妹狱医》
A32: 危险调查员 1-4 | B32: 漫画 | C32: 尖端 | D32: 完全版 | E32: 4 | F32: 25K | G32: 完结 | H32: 浦泽直树 | I32: 全新 | K32: 盒装 | L32: 留存 | M32: 222 | R32: 抖音
A33: 危险调查员 5-8 | B33: 漫画 | C33: 尖端 | D33: 完全版 | E33: 4 | F33: 25K | G33: 完结 | H33: 浦泽直树 | I33: 全新 | K33: 盒装 | L33: 留存 | M33: 224 | R33: 抖音
A34: 危险调查员 9-12 | B34: 漫画 | C34: 尖端 | D34: 完全版 | E34: 4 | F34: 25K | G34: 完结 | H34: 浦泽直树 | I34: 全新 | K34: 盒装 | L34: 留存 | R34: 京东
A35: 侦探学园Q 1 | B35: 漫画 | C35: 东立 | D35: 爱藏版 | E35: 1 | F35: 32K | G35: 连载中 | H35: 天树征丸 | I35: 全新 | J35: 首限 | L35: 留存 | R35: 抖音
A36: 侦探学园Q 2 | B36: 漫画 | C36: 东立 | D36: 爱藏版 | E36: 1 | F36: 32K | G36: 连载中 | H36: 天树征丸 | I36: 全新 | J36: 首限 | L36: 留存 | R36: 抖音
A37: 侦探学园Q 3 | B37: 漫画 | C37: 东立 | D37: 爱藏版 | E37: 1 | F37: 32K | G37: 连载中 | H37: 天树征丸 | I37: 全新 | J37: 首限 | L37: 留存 | M37: 32 | R37: 抖音
A38: 眨眼之声 1 | B38: 漫画 | C38: 东立 | D38: 台版 | E38: 1 | F38: 32K | G38: 连载中 | H38: 押见修造 | I38: 全新 | L38: 留存 | M38: 42 | R38: 抖音
A39: 魔都精兵的奴隶 1-19 | B39: 漫画 | C39: 东立 | D39: 台版 | E39: 19 | F39: 32K | G39: 连载中 | H39: タカヒロ | I39: 全新 | L39: 留存 | M39: 750 | R39: 闲鱼
A40: 魔都精兵的奴隶 20 | B40: 漫画 | C40: 东立 | D40: 台版 | E40: 1 | F40: 32K | G40: 连载中 | H40: タカヒロ | I40: 全新 | J40: 首 | L40: 留存 | M40: 60 | R40: 闲鱼
A41: 我内心糟糕的地方 1-11 | B41: 漫画 | C41: 东立 | D41: 台版 | E41: 11 | F41: 36K | G41: 连载中 | H41: 樱井纪雄 | I41: 全新 | L41: 留存 | M41: 326 | R41: 抖音
A42: 我内心糟糕的地方 12 | B42: 漫画 | C42: 东立 | D42: 台版 | E42: 1 | F42: 36K | G42: 连载中 | H42: 樱井纪雄 | I42: 全新 | L42: 留存 | M42: 31 | R42: 抖音 小号
A43: 葬送的芙莉莲 1-13 | B43: 漫画 | C43: 东立 | D43: 台版 | E43: 13 | F43: 32K | G43: 连载中 | H43: 山田钟人 | I43: 全新 | L43: 留存 | M43: 194 | R43: 淘宝
A44: 葬送的芙莉莲 14 | B44: 漫画 | C44: 东立 | D44: 台版 | E44: 1 | F44: 32K | G44: 连载中 | H44: 山田钟人 | I44: 全新 | L44: 留存 | M44: 31 | R44: 博客来
A45: 葬送的芙莉莲 15 | B45: 漫画 | C45: 东立 | D45: 台版 | E45: 1 | F45: 32K | G45: 连载中 | H45: 山田钟人 | I45: 全新 | L45: 留存 | M45: 9 | R45: 抖音
A46: 谭雅战记 1-30 | B46: 漫画 | C46: 角川 | D46: 台版 | E46: 30 | F46: 32K | G46: 连载中 | H46: カルロ・ゼン | I46: 全新 | L46: 留存 | M46: 859 | R46: 抖音
A47: 光逝去的夏天 1-6 | B47: 漫画 | C47: 角川 | D47: 台版 | E47: 6 | F47: 32K | G47: 连载中 | H47: モクモクれん | I47: 全新 | L47: 留存 | M47: 247 | R47: 抖音
A56: 碧蓝之海 1-23 | B56: 漫画 | C56: 东立 | D56: 台版 | E56: 23 | F56: 32K | G56: 连载中 | H56: 井上坚二 | I56: 全新 | L56: 留存 | M56: 634 | R56: 抖音
A57: 碧蓝之海 24 | B57: 漫画 | C57: 东立 | D57: 台版 | E57: 1 | F57: 32K | G57: 连载中 | H57: 井上坚二 | I57: 全新 | L57: 留存 | M57: 55 | R57: 闲鱼
A58: 碧蓝之海 25 | B58: 漫画 | C58: 东立 | D58: 台版 | E58: 1 | F58: 32K | G58: 连载中 | H58: 井上坚二 | I58: 全新 | L58: 留存 | R58: 乐淘
A59: 历史之眼 1-12 | B59: 漫画 | C59: 东立 | D59: 台版 | E59: 12 | F59: 32K | G59: 连载中 | H59: 岩明均 | I59: 全新 | L59: 留存 | M59: 370 | R59: 抖音 未处理
A60: 企业佣兵·艾坦 1-4 | B60: 漫画 | C60: 长鸿 | D60: 台版 | E60: 4 | F60: 32K | G60: 连载中 | H60: 山道七穂 | I60: 全新 | L60: 留存 | M60: 127 | R60: 抖音，限 卖
A61: 暗黑破坏神 1-27 | B61: 漫画 | C61: 尖端 | D61: 台版 | E61: 27 | F61: 32K | G61: 连载中 | H61: 萩原一至 | I61: 全新 | L61: 留存 | M61: 1050 | R61: 闲鱼，6已拆
A62: 死神 1-22 | B62: 漫画 | C62: 东立 | D62: 爱藏版 | E62: 22 | F62: 32K | G62: 连载中 | H62: 久保带人 | I62: 全新 | J62: 首限 | L62: 留存 | M62: 922 | R62: 抖音
A63: 死神 1 | B63: 漫画 | C63: 东立 | D63: 爱藏版 | E63: 1 | F63: 32K | G63: 连载中 | H63: 久保带人 | I63: 全新 | J63: 首限 | L63: 留存 | R63: 抖音 42
A64: 死神 2 | B64: 漫画 | C64: 东立 | D64: 爱藏版 | E64: 1 | F64: 32K | G64: 连载中 | H64: 久保带人 | I64: 全新 | J64: 首限 | L64: 留存 | R64: 抖音 45
A65: 死神 3 | B65: 漫画 | C65: 东立 | D65: 爱藏版 | E65: 1 | F65: 32K | G65: 连载中 | H65: 久保带人 | I65: 全新 | J65: 首限 | L65: 留存 | R65: 抖音 45
A66: 死神 4 | B66: 漫画 | C66: 东立 | D66: 爱藏版 | E66: 1 | F66: 32K | G66: 连载中 | H66: 久保带人 | I66: 全新 | J66: 首限 | L66: 留存 | R66: 抖音 45
A67: 死神 5 | B67: 漫画 | C67: 东立 | D67: 爱藏版 | E67: 1 | F67: 32K | G67: 连载中 | H67: 久保带人 | I67: 全新 | J67: 首限 | L67: 留存 | R67: 抖音 45
A68: 死神 6 | B68: 漫画 | C68: 东立 | D68: 爱藏版 | E68: 1 | F68: 32K | G68: 连载中 | H68: 久保带人 | I68: 全新 | J68: 首限 | L68: 留存 | R68: 抖音 42
A69: 死神 7 | B69: 漫画 | C69: 东立 | D69: 爱藏版 | E69: 1 | F69: 32K | G69: 连载中 | H69: 久保带人 | I69: 全新 | J69: 首限 | L69: 留存 | R69: 抖音 43
A70: 死神 8 | B70: 漫画 | C70: 东立 | D70: 爱藏版 | E70: 1 | F70: 32K | G70: 连载中 | H70: 久保带人 | I70: 全新 | J70: 首限 | L70: 留存 | R70: 抖音 44
A71: 死神 9 | B71: 漫画 | C71: 东立 | D71: 爱藏版 | E71: 1 | F71: 32K | G71: 连载中 | H71: 久保带人 | I71: 全新 | J71: 首限 | L71: 留存 | R71: 抖音 44
A72: 死神 10 | B72: 漫画 | C72: 东立 | D72: 爱藏版 | E72: 1 | F72: 32K | G72: 连载中 | H72: 久保带人 | I72: 全新 | J72: 首限 | L72: 留存 | R72: 抖音 40
A73: 死神 11 | B73: 漫画 | C73: 东立 | D73: 爱藏版 | E73: 1 | F73: 32K | G73: 连载中 | H73: 久保带人 | I73: 全新 | J73: 首限 | L73: 留存 | R73: 抖音 45
A74: 死神 12 | B74: 漫画 | C74: 东立 | D74: 爱藏版 | E74: 1 | F74: 32K | G74: 连载中 | H74: 久保带人 | I74: 全新 | J74: 首限 | L74: 留存 | R74: 抖音 35
... A84: 死神 22 | B84: 漫画 | C84: 东立 | D84: 爱藏版 | E84: 1 | F84: 32K | G84: 连载中 | H84: 久保带人 | I84: 全新 | J84: 首限 | L84: 留存 | R84: 抖音 34
A85: 银魂 1-10 | B85: 漫画 | C85: 东立 | D85: 爱藏版 | E85: 10 | F85: 32K | G85: 连载中 | H85: 空知英秋 | I85: 全新 | J85: 首限 | L85: 留存 | M85: 344 | R85: 抖音
A86: 银魂 1 | B86: 漫画 | C86: 东立 | D86: 爱藏版 | E86: 1 | F86: 32K | G86: 连载中 | H86: 空知英秋 | I86: 全新 | J86: 首限 | L86: 留存 | R86: 抖音 28
A87: 银魂 2 | B87: 漫画 | C87: 东立 | D87: 爱藏版 | E87: 1 | F87: 32K | G87: 连载中 | H87: 空知英秋 | I87: 全新 | J87: 首限 | L87: 留存 | R87: 抖音 34
A88: 银魂 3 | B88: 漫画 | C88: 东立 | D88: 爱藏版 | E88: 1 | F88: 32K | G88: 连载中 | H88: 空知英秋 | I88: 全新 | J88: 首限 | L88: 留存 | R88: 抖音 35
A89: 银魂 4 | B89: 漫画 | C89: 东立 | D89: 爱藏版 | E89: 1 | F89: 32K | G89: 连载中 | H89: 空知英秋 | I89: 全新 | J89: 首限 | L89: 留存 | R89: 抖音 34
A90: 银魂 5 | B90: 漫画 | C90: 东立 | D90: 爱藏版 | E90: 1 | F90: 32K | G90: 连载中 | H90: 空知英秋 | I90: 全新 | J90: 首限 | L90: 留存 | R90: 抖音 33
A91: 银魂 6 | B91: 漫画 | C91: 东立 | D91: 爱藏版 | E91: 1 | F91: 32K | G91: 连载中 | H91: 空知英秋 | I91: 全新 | J91: 首限 | L91: 留存 | R91: 抖音 37
A92: 银魂 7 | B92: 漫画 | C92: 东立 | D92: 爱藏版 | E92: 1 | F92: 32K | G92: 连载中 | H92: 空知英秋 | I92: 全新 | J92: 首限 | L92: 留存 | R92: 抖音 35
A93: 银魂 8 | B93: 漫画 | C93: 东立 | D93: 爱藏版 | E93: 1 | F93: 32K | G93: 连载中 | H93: 空知英秋 | I93: 全新 | J93: 首限 | L93: 留存 | R93: 抖音 37
A94: 银魂 9 | B94: 漫画 | C94: 东立 | D94: 爱藏版 | E94: 1 | F94: 32K | G94: 连载中 | H94: 空知英秋 | I94: 全新 | J94: 首限 | L94: 留存 | R94: 抖音（预售） 37
A95: 银魂 10 | B95: 漫画 | C95: 东立 | D95: 爱藏版 | E95: 1 | F95: 32K | G95: 连载中 | H95: 空知英秋 | I95: 全新 | J95: 首限 | L95: 留存 | R95: 抖音（预售） 34
A96: 家有贱狗 1-4 | B96: 漫画 | C96: 东立 | D96: 爱藏版 | E96: 1 | F96: 32K | G96: 连载中 | H96: Terry山本 | I96: 全新 | J96: 首限 | L96: 留存 | M96: 124 | R96: 抖音
A97: 家有贱狗 1 | B97: 漫画 | C97: 东立 | D97: 爱藏版 | E97: 1 | F97: 32K | G97: 连载中 | H97: Terry山本 | I97: 全新 | J97: 首限 | L97: 留存 | R97: 抖音 28
A98: 家有贱狗 2 | B98: 漫画 | C98: 东立 | D98: 爱藏版 | E98: 1 | F98: 32K | G98: 连载中 | H98: Terry山本 | I98: 全新 | J98: 首限 | L98: 留存 | R98: 抖音 42
A99: 家有贱狗 3 | B99: 漫画 | C99: 东立 | D99: 爱藏版 | E99: 1 | F99: 32K | G99: 连载中 | H99: Terry山本 | I99: 全新 | J99: 首限 | L99: 留存 | R99: 抖音 26
A100: 家有贱狗 4 | B100: 漫画 | C100: 东立 | D100: 爱藏版 | E100: 1 | F100: 32K | G100: 连载中 | H100: Terry山本 | I100: 全新 | J100: 首限 | L100: 留存 | R100: 抖音 28
A101: 横行太保 1-10 | B101: 漫画 | C101: 尖端 | D101: 典藏版 | E101: 10 | F101: 25K | G101: 完结 | H101: 梅泽春人 | I101: 全新 | K101: 盒装 | L101: 留存
A102: 横行太保 11-20 | B102: 漫画 | C102: 尖端 | D102: 典藏版 | E102: 10 | F102: 25K | G102: 完结 | H102: 梅泽春人 | I102: 全新 | K102: 盒装 | L102: 留存 | M102: 415 | R102: 淘宝
A103: 明日同学的水手服 1-13 | B103: 漫画 | C103: 东立 | D103: 台版 | E103: 13 | F103: 32K | G103: 连载中 | H103: 博（Hiro） | I103: 全新 | L103: 留存 | M103: 223 | R103: 淘宝 胖猪号
A104: 青之芦苇 1-5 | B104: 漫画 | C104: 四川美术 | D104: 简中 | E104: 5 | F104: 32K | G104: 连载中 | H104: 小林有吾 | I104: 全新 | K104: 盒装 | L104: 留存 | M104: 34 | R104: 京东
A105: 青之芦苇 6-10 | B105: 漫画 | C105: 四川美术 | D105: 简中 | E105: 5 | F105: 32K | G105: 连载中 | H105: 小林有吾 | I105: 全新 | K105: 盒装 | L105: 留存 | M105: 34 | R105: 京东
A106: 玩玩的恋爱关系 1 | B106: 轻小说 | C106: 角川 | D106: 特装版 | E106: 1 | F106: 32K | G106: 连载中 | H106: 葵关南 | I106: 全新 | L106: 留存 | M106: 118 | R106: 京东（预售）
A107: 玩玩的恋爱关系 2 | B107: 轻小说 | C107: 角川 | D107: 特装版 | E107: 1 | F107: 32K | G107: 连载中 | H107: 葵关南 | I107: 全新 | L107: 留存
A108: 冷面天使 1 | B108: 漫画 | C108: 长鸿 | D108: 典藏版 | E108: 1 | F108: 25K | G108: 连载中 | H108: 八木教广 | I108: 全新 | L108: 留存 | M108: 35 | R108: 抖音
A109: 冷面天使 2 | B109: 漫画 | C109: 长鸿 | D109: 典藏版 | E109: 1 | F109: 25K | G109: 连载中 | H109: 八木教广 | I109: 全新 | L109: 留存 | M109: 31 | R109: 抖音
A110: 冷面天使 3 | B110: 漫画 | C110: 长鸿 | D110: 典藏版 | E110: 1 | F110: 25K | G110: 连载中 | H110: 八木教广 | I110: 全新 | L110: 留存 | M110: 38 | R110: 抖音
A111: 冷面天使 4 | B111: 漫画 | C111: 长鸿 | D111: 典藏版 | E111: 1 | F111: 25K | G111: 连载中 | H111: 八木教广 | I111: 全新 | L111: 留存 | M111: 32 | R111: 抖音
A112: 冷面天使 5 | B112: 漫画 | C112: 长鸿 | D112: 典藏版 | E112: 1 | F112: 25K | G112: 连载中 | H112: 八木教广 | I112: 全新 | L112: 留存 | M112: 48 | R112: 抖音
A113: 冷面天使 6 | B113: 漫画 | C113: 长鸿 | D113: 典藏版 | E113: 1 | F113: 25K | G113: 连载中 | H113: 八木教广 | I113: 全新 | L113: 留存 | M113: 39 | R113: 抖音
A114: 傀儡马戏团 | B114: 漫画 | C114: 青文 | D114: 完全版 | E114: 26 | F114: 25K | G114: 完结 | H114: 藤田和日郎 | I114: 全新 | K114: 盒装 | L114: 留存
A115: K-ON！轻音部 | B115: 漫画 | C115: 尖端 | D115: 45周年纪念版 | E115: 4 | F115: 32K | G115: 完结 | H115: kakifly | I115: 全新 | K115: 盒装 | L115: 留存 | M115: 148 | R115: 抖音（预售）
A116: 声之形 1-4 | B116: 漫画 | C116: 东立 | D116: 台版 | E116: 4 | F116: 32K | G116: 连载中 | H116: 大今良时 | I116: 全新 | K116: 盒装 | L116: 留存 | M116: 180 | R116: 抖音（预售）
A117: 四月是你的谎言 1-3 | B117: 漫画 | C117: 东立 | D117: 台版 | E117: 3 | F117: 25K | G117: 连载中 | H117: 新川直司 | I117: 全新 | K117: 盒装 | L117: 留存 | M117: 137 | R117: 抖音（预售）
...

Sheet 淘宝
A1: IP | B1: 系列名称 | C1: 名称 | D1: 买时状态 | E1: 状态 | F1: 总价 | G1: 成本价格 | H1: 卖出价格 | I1: 利润 | J1: 利润率 | K1: 备注
A2: 龙珠 | B2: HG | C2: 沙鲁全形态 | D2: 全新 | E2: 留存 | F2: 635 | K2: 预定 | M2: 总花销 | N2: =SUM(F:F) -> 19048
A3: 曼达洛人 | B3: FRS | C3: 贝斯卡金属盔甲 | D3: 全新 | E3: 留存 | F3: 275 | M3: 总卖出 | N3: =SUM(H:H) -> 7342
A4: 龙珠 | B4: SHF | C4: 婴儿车弗利萨 | D4: 全新 | E4: 留存 | F4: 444 | K4: 预定，已拆 | M4: 总卖出成本 | N4: =SUM(G:G) -> 5819
A5: 龙珠 | B5: HG | C5: 弗利萨全形态 | D5: 全新 | E5: 留存 | F5: 820 | K5: 预定 | M5: 利润 | N5: =SUM(I:I) -> 1523
A6: 龙珠 | B6: 桌面系列 | C6: 悟空全形态 | D6: 全新 | E6: 留存 | F6: 400 | K6: 预定 | M6: 利润率 | N6: =ROUND(N5/N3,4) -> 0.2074
A7: 龙珠 | B7: FiguartsZERO | C7: 超3龙拳 | D7: 全新 | E7: 留存 | F7: 653 | K7: 新版预定，已拆 | M7: 实际支出 | N7: =N2-N3 -> 11706
A8: 数码宝贝 | B8: FRS | C8: 机械暴龙兽 | D8: 全新 | E8: 留存 | F8: 277 | K8: 预定
A9: 龙珠 | B9: 出阵 | C9: 比克A款 | D9: 全新 | E9: 留存 | F9: 106 | K9: 预定
A10: 龙珠 | B10: 出阵 | C10: 比克B款 | D10: 全新 | E10: 留存 | F10: 104 | K10: 预定
A11: 龙珠 | B11: Gxmateria | C11: 超赛贝吉特 | D11: 全新 | E11: 留存 | F11: 51
A12: 龙珠 | B12: 出阵 | C12: 超赛特兰克斯 | D12: 全新 | E12: 留存 | F12: 51
A13: 龙珠 | B13: Gxmateria | C13: 短笛 魔贯光杀炮 | D13: 全新 | E13: 留存 | F13: 51
A14: 龙珠 | B14: LC | C14: 发波悟空 | D14: 全新 | E14: 留存 | F14: 148
A15: 龙珠 | B15: FES | C15: 12悟空 | D15: 全新 | E15: 留存 | F15: 82
A16: 龙珠 | B16: Grandista | C16: 孙悟饭 | D16: 全新 | E16: 留存 | F16: 194
A17: 龙珠 | B17: Grandista | C17: 超3悟空 | D17: 全新 | E17: 留存 | F17: 686
A18: 龙珠 | B18: 一番赏 | C18: 羁绊黑发贝吉塔 | D18: 全新 | E18: 留存 | F18: 380
A19: 龙珠 | B19: 一番赏 | C19: 羁绊黑发悟空 | D19: 全新 | E19: 留存 | F19: 312
A20: 龙珠 | C20: 水晶球 | D20: 全新 | E20: 留存 | F20: 51
A21: 龙珠 | B21: FiguartsZERO | C21: 邪念波 | D21: 全新 | E21: 留存 | F21: 709 | K21: 预定
A22: 龙珠 | B22: PLEX | C22: 拉蒂兹 | D22: 全新 | E22: 留存 | F22: 1698 | K22: 预定
A23: 更衣人偶坠入爱河 | B23: Taito | C23: 喜多川海梦 | D23: 全新 | E23: 留存 | F23: 252 | K23: 130重涂
A24: 龙珠 | B24: WCF | C24: 宝藏1 | D24: 全新 | E24: 卖出 | F24: 962 | G24: 802 | H24: 1219 | I24: =H24-G24 -> 417 | J24: =I24/G24 -> 0.51995012 | K24: 6件，留一件
A25: 鬼灭之刃 | B25: WCF | C25: 善逸 | D25: 全新 | E25: 卖出 | F25: 402 | G25: 268 | H25: 328 | I25: =H25-G25 -> 60 | J25: =I25/G25 -> 0.2238806 | K25: 3件，留一件
A26: 鬼灭之刃 | B26: WCF | C26: 伊之助 | D26: 全新 | E26: 卖出 | F26: 470 | G26: 344 | H26: 484 | I26: =H26-G26 -> 140 | J26: =I26/G26 -> 0.40697674 | K26: 3件，还剩一件除女装的四个
A27: 龙珠 | B27: 历史盒子 | C27: 超赛悟空2 | D27: 全新 | E27: 留存 | F27: 63
A28: 龙珠 | B28: BOS | C28: 未来悟饭 | D28: 全新 | E28: 卖出 | F28: 33 | G28: 33 | H28: 44 | I28: =H28-G28 -> 11 | J28: =I28/G28 -> 0.33333333
A29: 龙珠 | B29: 出阵 | C29: 悟饭 | D29: 全新 | E29: 卖出 | F29: 39 | G29: 39 | H29: 59 | I29: =H29-G29 -> 20 | J29: =I29/G29 -> 0.51282051
A30: 龙珠 | B30: 出阵 | C30: 比克 | D30: 全新 | E30: 卖出 | F30: 39 | G30: 39 | H30: 76 | I30: =H30-G30 -> 37 | J30: =I30/G30 -> 0.94871795
A31: 龙珠 | B31: 出阵 | C31: 悟饭 | D31: 全新 | E31: 卖出 | F31: 33 | G31: 33 | H31: 60 | I31: =H31-G31 -> 27 | J31: =I31/G31 -> 0.81818182
A32: 鬼灭之刃 | B32: WCF | C32: 主公大人面前2 | D32: 全新 | E32: 留存 | F32: 81
A33: 我与机器子 | B33: megahouse | C33: 机器子 | D33: 全新 | E33: 留存 | F33: 588
A34: 无职转生 | B34: 换装时刻 | C34: 红妈妈 | D34: 全新 | E34: 留存 | F34: 862
A35: 啦啦队系列 | B35: Hobby·sakura | C35: 阿雅 | D35: 全新 | E35: 卖出 | F35: 598 | G35: 598 | H35: 693 | I35: =H35-G35 -> 95 | J35: =I35/G35 -> 0.15886288 | K35: 普通版
A36: 啦啦队系列 | B36: Hobby·sakura | C36: 阿雅 | D36: 全新 | E36: 卖出 | F36: 598 | G36: 598 | H36: 595 | I36: =H36-G36 -> -3 | J36: =I36/G36 -> -0.0050167224 | K36: 普通版
A37: 啦啦队系列 | B37: Hobby·sakura | C37: 阿雅 | D37: 全新 | E37: 留存 | F37: 598 | K37: 普通版，卖
A38: 共鸣 | B38: 泡泡玛特 | C38: 龙珠载具系列 | D38: 全新 | E38: 留存 | F38: 469
A39: 初音未来 | B39: GSC | C39: 牛角初音 | D39: 全新 | E39: 留存 | F39: 819 | K39: GSC淘宝旗舰店
A40: 黑岩射手 | B40: Max Factory | C40: 黑岩射手 | D40: 全新 | E40: 卖出 | F40: 1291 | G40: 1291 | H40: 1674 | I40: =H40-G40 -> 383 | J40: =I40/G40 -> 0.29666925 | K40: 天猫国际，未发货补偿
A41: 命运-冠位指定 | B41: GSC | C41: 剑士-阿尔托莉雅·潘德拉贡 与 黑甲骑兵 | D41: 全新 | E41: 留存 | F41: 950
A42: 迪士尼 | B42: 玩偶 | C42: 布鲁托挂件 | D42: 全新 | E42: 卖出 | F42: 155 | G42: 155 | H42: 168 | I42: =H42-G42 -> 13 | J42: =I42/G42 -> 0.083870968
A43: 迪士尼 | B43: 玩偶 | C43: 饼饼+璐璐 | D43: 全新 | E43: 卖出 | F43: 374 | G43: 374 | H43: 427 | I43: =H43-G43 -> 53 | J43: =I43/G43 -> 0.14171123 | K43: 青花瓷
A44: 海贼王 | B44: WCF | C44: 鲤鱼旗 | D44: 全新 | E44: 卖出 | F44: 100 | G44: 100 | H44: 98 | I44: =H44-G44 -> -2 | J44: =I44/G44 -> -0.02
A45: 碧蓝航线 | B45: ELEGANT | C45: 圣路易斯 | D45: 全新 | E45: 卖出 | F45: 595 | G45: 595 | H45: 662 | I45: =H45-G45 -> 67 | J45: =I45/G45 -> 0.11260504
A46: 爱丽丝梦游仙境 | B46: APEX-TOYS | C46: 爱丽丝·里德尔 | D46: 全新 | E46: 卖出 | F46: 550 | G46: 550 | H46: 755 | I46: =H46-G46 -> 205 | J46: =I46/G46 -> 0.37272727

Sheet B站市集
A1: IP | B1: 系列名称 | C1: 名称 | D1: 买时状态 | E1: 购入价格 | F1: 状态 | G1: 总价 | H1: 卖出成本 | I1: 卖出价格 | J1: 利润 | K1: 利润率 | L1: 备注
A2: 狐妖小红娘 | B2: 盛夏绽放 泳装Ver. | C2: 涂山红红 | D2: 全新 | E2: 232 | F2: 卖出 | G2: =E2 -> 232 | H2: 232 | I2: 510 | J2: =I2-H2 -> 278 | K2: =J2/H2 -> 1.1982759 | N2: 总花销 | O2: =SUM(G:G) -> 8307
A3: 狐妖小红娘 | B3: 初见 手游版 | C3: 涂山苏苏 | D3: 全新 | E3: 189 | F3: 卖出 | G3: =E3 -> 189 | H3: 189 | I3: 328 | J3: =I3-H3 -> 139 | K3: =J3/H3 -> 0.73544974 | N3: 总卖出 | O3: =SUM(I:I) -> 1406
B4: 阿尔维娜 | C4: 阿尔维娜 | D4: 全新 | E4: 390 | F4: 留存 | G4: =E4 -> 390 | N4: 总卖出成本 | O4: =SUM(H:H) -> 846
A5: 少女前线 | C5: 她从雨中来 | D5: 全新 | E5: 550 | F5: 留存 | G5: =E5 -> 550 | N5: 利润 | O5: =SUM(J:J) -> 560
A6: 碧蓝航线 | B6: GSC | C6: 尾张 | D6: 全新 | E6: 763 | F6: 留存 | G6: =E6 -> 763 | L6: 25年9月 | N6: 利润率 | O6: =ROUND(O5/O4,4) -> 0.6619
B7: GSC | C7: 白银诺艾尔 泳装 | D7: 全新 | E7: 725 | F7: 留存 | G7: =E7 -> 725 | L7: 25年7月 | N7: 实际支出 | O7: =O2-O3 -> 6901
A8: 碧蓝航线 | B8: Mimeyoi | C8: 约克公爵 | D8: 全新 | E8: 705 | F8: 留存 | G8: =E8 -> 705
C9: 金瓯永固杯 | D9: 全新 | E9: 320 | F9: 卖出 | G9: =E9 -> 320 | H9: 320 | I9: 360 | J9: =I9-H9 -> 40 | K9: =J9/H9 -> 0.125
B10: 尺玉 | C10: 雪乃深冬 | D10: 全新 | E10: 480 | F10: 留存 | G10: =E10 -> 480 | L10: 25年12月
A11: 电锯人 | B11: BiCute Bunnies | C11: 蕾塞 | D11: 全新 | E11: 105 | F11: 卖出 | G11: =E11 -> 105 | H11: 105 | I11: 208 | J11: =I11-H11 -> 103 | K11: =J11/H11 -> 0.98095238 | L11: 26年1月
A12: 电锯人 | B12: BiCute Bunnies | C12: 蕾塞 | D12: 全新 | E12: 98 | F12: 留存 | G12: =E12 -> 98 | L12: 26年1月
A13: 约会大作战 | B13: 角川 | C13: 时崎狂三 富士见文库30周年纪念版 | D13: 全新 | E13: 710 | F13: 留存 | G13: =E13 -> 710 | L13: 26年2月
A14: EVA | B14: Alter | C14: 绫波丽 | D14: 全新 | E14: 900 | F14: 留存 | G14: =E14 -> 900 | L14: 26年2月
A15: 更衣人偶坠入爱河 | B15: GSC | C15: 喜多川海梦 黑江雫 | D15: 全新 | E15: 693 | F15: 留存 | G15: =E15 -> 693 | L15: 26年3月
A16: 鬼灭之刃 | B16: Alter | C16: 富冈义勇 | D16: 全新 | E16: 836 | F16: 留存 | G16: =E16 -> 836 | L16: 26年6月，闲鱼购入
A17: 电锯人 | B17: S-FIRE | C17: 蕾塞 | D17: 全新 | E17: 611 | F17: 留存 | G17: =E17 -> 611 | L17: 26年9月

Sheet 小程序
A1: IP | B1: 系列名称 | C1: 名称 | D1: 买时状态 | E1: 状态 | F1: 总价 | G1: 成本价格 | H1: 卖出价格 | I1: 利润 | J1: 利润率 | K1: 备注
A2: GSC | C2: 02国家队+少女前线DSR-50 | D2: 全新 | E2: 卖出 | F2: 899 | G2: 899 | H2: 1440 | I2: =H2-G2 -> 541 | J2: =I2/G2 -> 0.60177976 | K2: 福袋 | M2: 总花销 | N2: =SUM(F:F) -> 1797
A3: BANDAI | B3: SMSP | C3: 贝吉塔 | D3: 全新 | E3: 留存 | F3: 449 | M3: 总卖出 | N3: =SUM(H:H) -> 1440
A4: BANDAI | B4: SMSP | C4: 悟空 | D4: 全新 | E4: 留存 | F4: 449 | K4: 胖猪号 | M4: 总卖出成本 | N4: =SUM(G:G) -> 899
M5: 利润 | N5: =SUM(I:I) -> 541
M6: 利润率 | N6: =ROUND(N5/N4,4) -> 0.6018
M7: 实际支出 | N7: =N2-N3 -> 357

Sheet 入魂一番赏
A1: IP | B1: 系列名称 | C1: 名称 | D1: 买时状态 | E1: 状态 | F1: 总价 | G1: 卖出成本 | H1: 卖出价格 | I1: 利润 | J1: 利润率 | K1: 备注
A2: 约会大作战 | B2: GSC POP UP | C2: 时崎狂三 校服 L尺寸 | D2: 全新 | E2: 卖出 | F2: 240 | G2: 240 | H2: 285 | I2: =H2-G2 -> 45 | J2: =I2/G2 -> 0.1875 | K2: 24年10月 | M2: 总花销 | N2: =SUM(F:F) -> 10445
A3: 四月是你的谎言 | B3: GSC | C3: 宫园薰 | D3: 全新 | E3: 留存 | F3: 450 | K3: 24年11月 | M3: 总卖出 | N3: =SUM(H:H) -> 1121
A4: 初音未来 | B4: GSC | C4: 樱花未来 赏花装扮 | D4: 全新 | E4: 留存 | F4: 755 | K4: 25年4月 | M4: 总卖出成本 | N4: =SUM(G:G) -> 1005
A5: 蔚蓝档案 | B5: GSC | C5: 月雪宫子 | D5: 全新 | E5: 留存 | F5: 360 | K5: 25年5月 | M5: 利润 | N5: =SUM(I:I) -> 116
A6: 龙珠 | B6: 一番赏 | C6: 9号胶囊机车 | D6: 全新 | E6: 留存 | F6: 520 | K6: 25年1月 | M6: 利润率 | N6: =ROUND(N5/N4,4) -> 0.1154
A7: 龙珠 | B7: 一番赏 | C7: 比克大魔王last | D7: 全新 | E7: 留存 | F7: 750 | M7: 实际支出 | N7: =N2-N3 -> 9324
A8: 龙珠 | B8: 一番赏 | C8: 贝比 | D8: 全新 | E8: 留存 | F8: 230
A9: 龙珠 | B9: FiguartsZERO | C9: 大魔 界王神 | D9: 全新 | E9: 留存 | F9: 580
A10: 龙珠 | B10: Gxmateria | C10: 巴达克 | D10: 全新 | E10: 留存 | F10: 50
A11: 龙珠 | B11: 出阵 | C11: 人造人16号 | D11: 全新 | E11: 留存 | F11: 58
A12: 龙珠 | B12: 出阵 | C12: 弗利萨 | D12: 全新 | E12: 留存 | F12: 85
A13: 龙珠 | B13: 一番赏 | C13: 大魔 贝吉塔 布玛B赏 | D13: 全新 | E13: 留存 | F13: 90
A14: 龙珠 | B14: 一番赏 | C14: 大魔 比克 丹迪C赏 | D14: 全新 | E14: 留存 | F14: 180
A15: 龙珠 | B15: 一番赏 | C15: 大魔 古罗里奥D赏 | D15: 全新 | E15: 留存 | F15: 80
A16: 龙珠 | B16: 一番赏 | C16: 布尔玛 | D16: 全新 | E16: 留存 | F16: 107 | K16: 修业篇
A17: 龙珠 | B17: 一番赏 | C17: 雅木茶 | D17: 全新 | E17: 留存 | F17: 184 | K17: 修业篇
A18: 龙珠 | B18: 一番赏 | C18: 库林&悟空 | D18: 全新 | E18: 留存 | F18: 200 | K18: 修业篇
A19: 龙珠 | B19: 一番赏 | C19: 龟仙人 | D19: 全新 | E19: 留存 | F19: 315 | K19: 修业篇
A20: 龙珠 | B20: 一番赏 | C20: LAST立牌 | D20: 全新 | E20: 留存 | F20: 360 | K20: 少年篇
A21: 龙珠 | B21: 一番赏 | C21: 海龟 | D21: 全新 | E21: 留存 | F21: 55 | K21: 少年篇
A22: 龙珠 | B22: 一番赏 | C22: 库林 | D22: 全新 | E22: 留存 | F22: 78 | K22: 少年篇
A23: 龙珠 | B23: 一番赏 | C23: 立牌 | D23: 全新 | E23: 留存 | F23: 40 | K23: 少年篇 一整套
A24: 龙珠 | B24: 一番赏 | C24: 占卜婆婆 | D24: 全新 | E24: 留存 | F24: 62 | K24: 少年篇
A25: 龙珠 | B25: 一番赏 | C25: 亚奇洛贝 | D25: 全新 | E25: 留存 | F25: 55 | K25: 少年篇
A26: 龙珠 | B26: 一番赏 | C26: 阿修 | D26: 全新 | E26: 留存 | F26: 58 | K26: 少年篇
A27: 龙珠 | B27: 一番赏 | C27: 小舞 | D27: 全新 | E27: 留存 | F27: 58 | K27: 少年篇 乌龙换的
... A37: 龙珠 | B37: 一番赏 | C37: 立牌 | D37: 全新 | E37: 留存 | F37: 3 | K37: CROSS H赏
A38: 龙珠 | B38: FiguartsZERO | C38: 战斗的轨迹 | D38: 全新 | E38: 留存 | F38: 401
A39: 龙珠 | B39: 一番赏 | C39: 悟饭 | D39: 全新 | E39: 留存 | F39: 190 | K39: 40周年 其二
A40: 龙珠 | B40: 一番赏 | C40: 库林 | D40: 全新 | E40: 留存 | F40: 255 | K40: 40周年 其二
A41: 龙珠 | B41: 一番赏 | C41: 贝吉塔 | D41: 全新 | E41: 留存 | F41: 190 | K41: 40周年 其二
A42: 龙珠 | B42: 一番赏 | C42: 比克 | D42: 全新 | E42: 留存 | F42: 300 | K42: 40周年 其二
A43: 龙珠 | B43: 一番赏 | C43: A悟空+Last神龙 | D43: 全新 | E43: 留存 | F43: 590 | K43: 40周年 其二
A44: 龙珠 | B44: 一番赏 | C44: LAST | D44: 全新 | E44: 留存 | F44: 426 | K44: 载具2篇
A45: 龙珠 | B45: BOS | C45: 超级赛亚人 孙悟饭Ⅱ | D45: 全新 | E45: 留存 | F45: 55
A46: 龙珠 | B46: 历史盒子 | C46: 胖布欧 | D46: 全新 | E46: 留存 | F46: 55
A47: 龙珠 | B47: 历史盒子 | C47: 布尔玛 | D47: 全新 | E47: 留存 | F47: 70
A48: 龙珠 | B48: 一番赏 | C48: LAST | D48: 全新 | E48: 卖出 | F48: 365 | G48: 365 | H48: 396 | I48: =H48-G48 -> 31 | J48: =I48/G48 -> 0.084931507 | K48: 红缎带军团
A49: 龙珠 | B49: 一番赏 | C49: D赏 潜水艇 | D49: 全新 | E49: 卖出 | F49: 400 | G49: 400 | H49: 440 | I49: =H49-G49 -> 40 | J49: =I49/G49 -> 0.1 | K49: 红缎带军团

Sheet 总计
A1: 总花销 | B1: =SUM(日淘!R3+闲鱼!P2+泡泡玛特!O2+并夕夕!N2+预定!Q2+抖音!N2+'套书+单行本'!W2+'散本+未完结'!U2+淘宝!N2+B站市集!O2+小程序!N2+入魂一番赏!N2) -> 472297
A2: 总卖出 | B2: =SUM(日淘!R4+闲鱼!P3+泡泡玛特!O3+并夕夕!N3+预定!Q3+抖音!N3+'套书+单行本'!W3+'散本+未完结'!U3+淘宝!N3+B站市集!O3+小程序!N3+入魂一番赏!N3) -> 171519
A3: 总卖出成本 | B3: =SUM(日淘!R5+闲鱼!P4+泡泡玛特!O4+并夕夕!N4+预定!Q4+抖音!N4+'套书+单行本'!W4+'散本+未完结'!U4+淘宝!N4+B站市集!O4+小程序!N4+入魂一番赏!N4) -> 145530
A4: 利润 | B4: =SUM(日淘!R6+闲鱼!P5+泡泡玛特!O5+并夕夕!N5+预定!Q5+抖音!N5+'套书+单行本'!W5+'散本+未完结'!U5+淘宝!N5+B站市集!O5+小程序!N5+入魂一番赏!N5) -> 25989
A5: 利润率 | B5: =ROUND(B4/B3,4) -> 0.1786
A6: 实际支出 | B6: =SUM(日淘!R8+闲鱼!P7+泡泡玛特!O7+并夕夕!N7+预定!Q7+抖音!N7+'套书+单行本'!W7+'散本+未完结'!U7+淘宝!N7+B站市集!O7+小程序!N7+入魂一番赏!N7) -> 300778
